{
  "Grand Ringmail":{
    "subType":"Armour/Energy Shield",
    "implicitModTypes":[],
    "socketLimit":6,
    "tags":{
      "default":true
    },
    "type":"Body Armour",
    "armour":{
      "ArmourBaseMin":545,
      "ArmourBaseMax":627,
      "MovementPenalty":5,
      "EnergyShieldBaseMin":110,
      "EnergyShieldBaseMax":127
    },
    "req":{
      "int":133,
      "level":73
    },
    "influenceTags":{
      "tangle":"body_armour_tangle",
      "shaper":"body_armour_shaper",
      "cleansing":"body_armour_cleansing",
      "elder":"body_armour_elder",
      "eyrie":"body_armour_eyrie",
      "adjudicator":"body_armour_adjudicator",
      "crusader":"body_armour_crusader",
      "basilisk":"body_armour_basilisk"
    }
  },
  "Paladin's Hauberk":{
    "implicitModTypes":[],
    "tags":[],
    "armour":{
      "ArmourBaseMax":721,
      "EnergyShieldBaseMin":126,
      "EnergyShieldBaseMax":145
    },
    "req":{
      "int":151,
      "level":78
    },
    "influenceTags":[]
  },
  "Sacred Chainmail":{
    "implicitModTypes":[],
    "tags":[],
    "armour":{
      "ArmourBaseMin":723,
      "ArmourBaseMax":831,
      "EnergyShieldBaseMax":167
    },
    "req":{
      "int":173,
      "level":84
    },
    "influenceTags":[]
  },
  "Padded Vest":{
    "subType":"Evasion/Energy Shield",
    "implicitModTypes":[],
    "tags":[],
    "armour":{
      "EvasionBaseMin":27,
      "EvasionBaseMax":38,
      "MovementPenalty":3,
      "EnergyShieldBaseMin":9,
      "EnergyShieldBaseMax":13
    },
    "req":{
      "dex":10
    },
    "influenceTags":[]
  },
  "Chestplate":{
    "subType":"Armour",
    "implicitModTypes":[],
    "tags":[],
    "armour":{
      "ArmourBaseMin":68,
      "ArmourBaseMax":89
    },
    "req":{
      "str":25
    },
    "influenceTags":[]
  },
  "Copper Plate":{
    "implicitModTypes":[],
    "tags":[],
    "armour":{
      "ArmourBaseMin":176,
      "ArmourBaseMax":221
    },
    "req":{
      "str":53,
      "level":17
    },
    "influenceTags":[]
  },
  "War Plate":{
    "implicitModTypes":[],
    "tags":[],
    "armour":{
      "ArmourBaseMin":216,
      "ArmourBaseMax":248
    },
    "req":{
      "str":63,
      "level":21
    },
    "influenceTags":[]
  },
  "Full Plate":{
    "implicitModTypes":[],
    "tags":[],
    "armour":{
      "ArmourBaseMin":284,
      "ArmourBaseMax":319
    },
    "req":{
      "str":81,
      "level":28
    },
    "influenceTags":[]
  },
  "Arena Plate":{
    "implicitModTypes":[],
    "tags":[],
    "armour":{
      "ArmourBaseMin":324,
      "ArmourBaseMax":389
    },
    "req":{
      "str":91,
      "level":32
    },
    "influenceTags":[]
  },
  "Lordly Plate":{
    "implicitModTypes":[],
    "tags":[],
    "armour":{
      "ArmourBaseMin":353,
      "ArmourBaseMax":417
    },
    "req":{
      "str":99,
      "level":35
    },
    "influenceTags":[]
  },
  "Bronze Plate":{
    "implicitModTypes":[],
    "tags":[],
    "armour":{
      "ArmourBaseMin":373,
      "ArmourBaseMax":429
    },
    "req":{
      "str":104,
      "level":37
    },
    "influenceTags":[]
  },
  "Battle Plate":{
    "implicitModTypes":[],
    "tags":[],
    "armour":{
      "ArmourBaseMin":412,
      "ArmourBaseMax":474
    },
    "req":{
      "str":114,
      "level":41
    },
    "influenceTags":[]
  },
  "Sun Plate":{
    "implicitModTypes":[],
    "tags":[],
    "armour":{
      "ArmourBaseMin":451,
      "ArmourBaseMax":506
    },
    "req":{
      "str":124,
      "level":45
    },
    "influenceTags":[]
  },
  "Colosseum Plate":{
    "implicitModTypes":[],
    "tags":[],
    "armour":{
      "ArmourBaseMin":491,
      "ArmourBaseMax":589
    },
    "req":{
      "str":134,
      "level":49
    },
    "influenceTags":[]
  },
  "Majestic Plate":{
    "implicitModTypes":[],
    "tags":[],
    "armour":{
      "ArmourBaseMin":530,
      "ArmourBaseMax":625
    },
    "req":[],
    "influenceTags":[]
  },
  "Golden Plate":{
    "implicitModTypes":[],
    "tags":[],
    "armour":{
      "ArmourBaseMin":559,
      "ArmourBaseMax":643
    },
    "req":{
      "str":152,
      "level":56
    },
    "influenceTags":[]
  },
  "Crusader Plate":{
    "implicitModTypes":[],
    "tags":[],
    "armour":{
      "ArmourBaseMin":601,
      "ArmourBaseMax":691
    },
    "req":{
      "str":160,
      "level":59
    },
    "influenceTags":[]
  },
  "Astral Plate":{
    "influenceTags":[],
    "implicitModTypes":[["elemental","resistance"]],
    "implicit":"+(8-12)% to all Elemental Resistances",
    "tags":[],
    "armour":{
      "ArmourBaseMin":711,
      "ArmourBaseMax":782
    },
    "req":{
      "str":180,
      "level":62
    }
  },
  "Golden Mantle":{
    "influenceTags":[],
    "implicitModTypes":[[]],
    "implicit":"+(15-25)% to all Elemental Resistances",
    "subType":"Armour/Evasion/Energy Shield",
    "tags":[],
    "armour":{
      "EvasionBaseMin":75,
      "EvasionBaseMax":86,
      "EnergyShieldBaseMax":19
    },
    "req":{
      "dex":8,
      "level":20
    }
  },
  "Grasping Mail":{
    "implicitModTypes":[],
    "tags":[],
    "armour":{
      "ArmourBaseMax":250,
      "EvasionBaseMin":217,
      "EnergyShieldBaseMin":44,
      "EnergyShieldBaseMax":51
    },
    "req":{
      "dex":60,
      "level":70
    },
    "influenceTags":[]
  },
  "Gladiator Plate":{
    "implicitModTypes":[],
    "tags":[],
    "armour":{
      "ArmourBaseMin":738,
      "ArmourBaseMax":848
    },
    "req":{
      "str":177,
      "level":65
    },
    "influenceTags":[]
  },
  "Glorious Plate":{
    "implicitModTypes":[],
    "tags":[],
    "armour":{
      "ArmourBaseMin":776,
      "ArmourBaseMax":892
    },
    "req":{
      "str":191
    },
    "influenceTags":[]
  },
  "Titan Plate":{
    "implicitModTypes":[],
    "tags":[],
    "armour":{
      "ArmourBaseMin":877,
      "ArmourBaseMax":1009
    },
    "req":{
      "str":222
    },
    "influenceTags":[]
  },
  "Sacrificial Garb":{
    "influenceTags":[],
    "implicitModTypes":[["gem"]],
    "implicit":"+1 to Level of all Vaal Skill Gems",
    "tags":[],
    "armour":{
      "ArmourBaseMax":378,
      "EvasionBaseMin":329,
      "EnergyShieldBaseMin":67,
      "EnergyShieldBaseMax":77
    },
    "req":{
      "dex":66,
      "level":72
    }
  },
  "Legion Plate":{
    "implicitModTypes":[],
    "tags":[],
    "armour":{
      "ArmourBaseMin":1018,
      "ArmourBaseMax":1171
    },
    "req":{
      "str":254
    },
    "influenceTags":[]
  },
  "Royal Plate":{
    "implicitModTypes":[],
    "tags":[],
    "armour":{
      "ArmourBaseMin":1183,
      "ArmourBaseMax":1360
    },
    "req":{
      "str":293
    },
    "influenceTags":[]
  },
  "Shabby Jerkin":{
    "subType":"Evasion",
    "implicitModTypes":[],
    "tags":[],
    "armour":{
      "EvasionBaseMin":29
    },
    "req":{
      "dex":14
    },
    "influenceTags":[]
  },
  "Necrotic Armour":{
    "implicitModTypes":[],
    "tags":[],
    "armour":[],
    "req":[],
    "influenceTags":[]
  },
  "Torturer Garb":{
    "implicitModTypes":[],
    "tags":[],
    "armour":[],
    "req":[],
    "influenceTags":[]
  },
  "Sanguine Raiment":{
    "implicitModTypes":[],
    "tags":[],
    "armour":[],
    "req":[],
    "influenceTags":[]
  },
  "Oiled Coat":{
    "implicitModTypes":[],
    "tags":[],
    "armour":{
      "EvasionBaseMax":146,
      "EnergyShieldBaseMax":33
    },
    "req":{
      "level":22
    },
    "influenceTags":[]
  },
  "Sadist Garb":{
    "implicitModTypes":[],
    "tags":[],
    "armour":{
      "EvasionBaseMin":427,
      "EnergyShieldBaseMin":93,
      "EnergyShieldBaseMax":107
    },
    "req":{
      "dex":103,
      "int":109
    },
    "influenceTags":[]
  },
  "Strapped Leather":{
    "implicitModTypes":[],
    "tags":[],
    "armour":{
      "EvasionBaseMin":98
    },
    "req":[],
    "influenceTags":[]
  },
  "Buckskin Tunic":{
    "implicitModTypes":[],
    "tags":[],
    "armour":[],
    "req":[],
    "influenceTags":[]
  },
  "Wild Leather":{
    "implicitModTypes":[],
    "tags":[],
    "armour":{
      "EvasionBaseMin":255,
      "EvasionBaseMax":306
    },
    "req":[],
    "influenceTags":[]
  },
  "Full Leather":{
    "implicitModTypes":[],
    "tags":[],
    "armour":{
      "EvasionBaseMax":327
    },
    "req":[],
    "influenceTags":[]
  },
  "Sun Leather":{
    "implicitModTypes":[],
    "tags":[],
    "armour":{
      "EvasionBaseMax":382
    },
    "req":[],
    "influenceTags":[]
  },
  "Thief's Garb":{
    "implicitModTypes":[],
    "tags":[],
    "armour":{
      "EvasionBaseMax":396
    },
    "req":[],
    "influenceTags":[]
  },
  "Eelskin Tunic":{
    "implicitModTypes":[],
    "tags":[],
    "armour":[],
    "req":[],
    "influenceTags":[]
  },
  "Frontier Leather":{
    "implicitModTypes":[],
    "tags":[],
    "armour":{
      "EvasionBaseMax":495
    },
    "req":[],
    "influenceTags":[]
  },
  "Glorious Leather":{
    "implicitModTypes":[],
    "tags":[],
    "armour":{
      "EvasionBaseMax":519
    },
    "req":[],
    "influenceTags":[]
  },
  "Coronal Leather":{
    "implicitModTypes":[],
    "tags":[],
    "armour":{
      "EvasionBaseMax":579
    },
    "req":[],
    "influenceTags":[]
  },
  "Cutthroat's Garb":{
    "implicitModTypes":[],
    "tags":[],
    "armour":{
      "EvasionBaseMax":594
    },
    "req":[],
    "influenceTags":[]
  },
  "Sharkskin Tunic":{
    "implicitModTypes":[],
    "tags":[],
    "armour":[],
    "req":[],
    "influenceTags":[]
  },
  "Destiny Leather":{
    "implicitModTypes":[],
    "tags":[],
    "armour":[],
    "req":[],
    "influenceTags":[]
  },
  "Exquisite Leather":{
    "implicitModTypes":[],
    "tags":[],
    "armour":{
      "EvasionBaseMin":704,
      "EvasionBaseMax":810
    },
    "req":{
      "dex":170
    },
    "influenceTags":[]
  },
  "Zodiac Leather":{
    "implicitModTypes":[],
    "tags":[],
    "armour":{
      "EvasionBaseMin":854,
      "EvasionBaseMax":982
    },
    "req":{
      "dex":197
    },
    "influenceTags":[]
  },
  "Assassin's Garb":{
    "influenceTags":[],
    "implicitModTypes":[["speed"]],
    "implicit":"3% increased Movement Speed",
    "tags":[],
    "armour":{
      "EvasionBaseMin":737,
      "EvasionBaseMax":811
    },
    "req":{
      "dex":183
    }
  },
  "Blood Raiment":{
    "implicitModTypes":[],
    "tags":[],
    "armour":{
      "EvasionBaseMin":436,
      "EvasionBaseMax":501
    },
    "req":{
      "int":90
    },
    "influenceTags":[]
  },
  "Varnished Coat":{
    "implicitModTypes":[],
    "tags":[],
    "armour":{
      "EvasionBaseMin":387,
      "EvasionBaseMax":434,
      "EnergyShieldBaseMin":79
    },
    "req":{
      "dex":96
    },
    "influenceTags":[]
  },
  "Supreme Leather":{
    "implicitModTypes":[],
    "tags":[],
    "armour":{
      "EvasionBaseMin":894,
      "EvasionBaseMax":1028
    },
    "req":[],
    "influenceTags":[]
  },
  "Astral Leather":{
    "implicitModTypes":[],
    "tags":[],
    "armour":{
      "EvasionBaseMin":1037,
      "EvasionBaseMax":1193
    },
    "req":[],
    "influenceTags":[]
  },
  "Syndicate's Garb":{
    "implicitModTypes":[],
    "tags":[],
    "armour":{
      "EvasionBaseMin":1205,
      "EvasionBaseMax":1386
    },
    "req":[],
    "influenceTags":[]
  },
  "Simple Robe":{
    "subType":"Energy Shield",
    "implicitModTypes":[],
    "tags":[],
    "armour":[],
    "req":[],
    "influenceTags":[]
  },
  "Sentinel Jacket":{
    "implicitModTypes":[],
    "tags":[],
    "armour":{
      "EvasionBaseMin":330,
      "EvasionBaseMax":370,
      "EnergyShieldBaseMax":76
    },
    "req":[],
    "influenceTags":[]
  },
  "Crypt Armour":{
    "implicitModTypes":[],
    "tags":[],
    "armour":{
      "EvasionBaseMin":308,
      "EvasionBaseMax":369
    },
    "req":{
      "dex":82
    },
    "influenceTags":[]
  },
  "Lacquered Garb":{
    "implicitModTypes":[],
    "tags":[],
    "armour":{
      "EvasionBaseMin":286
    },
    "req":{
      "level":52
    },
    "influenceTags":[]
  },
  "Scarlet Raiment":{
    "implicitModTypes":[],
    "tags":[],
    "armour":{
      "EvasionBaseMin":156,
      "EnergyShieldBaseMin":34,
      "EnergyShieldBaseMax":39
    },
    "req":{
      "dex":43
    },
    "influenceTags":[]
  },
  "Sleek Coat":{
    "implicitModTypes":[],
    "tags":[],
    "armour":{
      "EvasionBaseMin":243,
      "EvasionBaseMax":287
    },
    "req":[],
    "influenceTags":[]
  },
  "Silken Vest":{
    "implicitModTypes":[],
    "tags":[],
    "armour":{
      "EnergyShieldBaseMin":30
    },
    "req":{
      "level":11
    },
    "influenceTags":[]
  },
  "Scholar's Robe":{
    "implicitModTypes":[],
    "tags":[],
    "armour":[],
    "req":{
      "int":55,
      "level":18
    },
    "influenceTags":[]
  },
  "Silken Garb":{
    "implicitModTypes":[],
    "tags":[],
    "armour":{
      "EnergyShieldBaseMax":64
    },
    "req":[],
    "influenceTags":[]
  },
  "Mage's Vestment":{
    "implicitModTypes":[],
    "tags":[],
    "armour":{
      "EnergyShieldBaseMax":69
    },
    "req":[],
    "influenceTags":[]
  },
  "Silk Robe":{
    "implicitModTypes":[],
    "tags":[],
    "armour":{
      "EnergyShieldBaseMax":80
    },
    "req":[],
    "influenceTags":[]
  },
  "Cabalist Regalia":{
    "implicitModTypes":[],
    "tags":[],
    "armour":{
      "EnergyShieldBaseMax":88
    },
    "req":[],
    "influenceTags":[]
  },
  "Sage's Robe":{
    "implicitModTypes":[],
    "tags":[],
    "armour":[],
    "req":[],
    "influenceTags":[]
  },
  "Silken Wrap":{
    "implicitModTypes":[],
    "tags":[],
    "armour":[],
    "req":[],
    "influenceTags":[]
  },
  "Conjurer's Vestment":{
    "implicitModTypes":[],
    "tags":[],
    "armour":{
      "EnergyShieldBaseMin":94,
      "EnergyShieldBaseMax":105
    },
    "req":[],
    "influenceTags":[]
  },
  "Spidersilk Robe":{
    "implicitModTypes":[],
    "tags":[],
    "armour":{
      "EnergyShieldBaseMin":101,
      "EnergyShieldBaseMax":117
    },
    "req":[],
    "influenceTags":[]
  },
  "Destroyer Regalia":{
    "implicitModTypes":[],
    "tags":[],
    "armour":{
      "EnergyShieldBaseMax":129
    },
    "req":[],
    "influenceTags":[]
  },
  "Savant's Robe":{
    "implicitModTypes":[],
    "tags":[],
    "armour":{
      "EnergyShieldBaseMin":115,
      "EnergyShieldBaseMax":132
    },
    "req":[],
    "influenceTags":[]
  },
  "Necromancer Silks":{
    "implicitModTypes":[],
    "tags":[],
    "armour":{
      "EnergyShieldBaseMin":123,
      "EnergyShieldBaseMax":147
    },
    "req":[],
    "influenceTags":[]
  },
  "Occultist's Vestment":{
    "influenceTags":[],
    "implicitModTypes":[["caster_damage","damage","caster"]],
    "implicit":"(3-10)% increased Spell Damage",
    "tags":[],
    "armour":{
      "EnergyShieldBaseMin":137
    },
    "req":[]
  },
  "Quilted Jacket":{
    "implicitModTypes":[],
    "tags":[],
    "armour":{
      "EnergyShieldBaseMin":46
    },
    "req":{
      "level":40
    },
    "influenceTags":[]
  },
  "Bone Armour":{
    "implicitModTypes":[],
    "tags":[],
    "armour":{
      "EvasionBaseMin":194,
      "EvasionBaseMax":233
    },
    "req":[],
    "influenceTags":[]
  },
  "Waxed Garb":{
    "implicitModTypes":[],
    "tags":[],
    "armour":{
      "EvasionBaseMin":178,
      "EvasionBaseMax":205
    },
    "req":{
      "dex":48
    },
    "influenceTags":[]
  },
  "Crimson Raiment":{
    "implicitModTypes":[],
    "tags":[],
    "armour":{
      "EvasionBaseMin":264,
      "EvasionBaseMax":304
    },
    "req":{
      "dex":71
    },
    "influenceTags":[]
  },
  "Widowsilk Robe":{
    "implicitModTypes":[],
    "tags":[],
    "armour":{
      "EnergyShieldBaseMin":157,
      "EnergyShieldBaseMax":181
    },
    "req":{
      "int":187
    },
    "influenceTags":[]
  },
  "Vaal Regalia":{
    "implicitModTypes":[],
    "tags":[],
    "armour":{
      "EnergyShieldBaseMin":171
    },
    "req":[],
    "influenceTags":[]
  },
  "Arcane Vestment":{
    "implicitModTypes":[],
    "tags":[],
    "armour":{
      "EnergyShieldBaseMin":196,
      "EnergyShieldBaseMax":225
    },
    "req":[],
    "influenceTags":[]
  },
  "Nightweave Robe":{
    "implicitModTypes":[],
    "tags":[],
    "armour":{
      "EnergyShieldBaseMin":227,
      "EnergyShieldBaseMax":260
    },
    "req":[],
    "influenceTags":[]
  },
  "Twilight Regalia":{
    "implicitModTypes":[],
    "tags":[],
    "armour":{
      "EnergyShieldBaseMin":262,
      "EnergyShieldBaseMax":302
    },
    "req":[],
    "influenceTags":[]
  },
  "Scale Vest":{
    "subType":"Armour/Evasion",
    "implicitModTypes":[],
    "tags":[],
    "armour":[],
    "req":[],
    "influenceTags":[]
  },
  "Carnal Armour":{
    "influenceTags":[],
    "implicitModTypes":[["resource","mana"]],
    "implicit":"+(20-25) to maximum Mana",
    "tags":[],
    "armour":{
      "EvasionBaseMax":388,
      "EnergyShieldBaseMax":113
    },
    "req":{
      "int":122
    }
  },
  "Padded Jacket":{
    "implicitModTypes":[],
    "tags":[],
    "armour":{
      "EvasionBaseMin":102,
      "EvasionBaseMax":128,
      "EnergyShieldBaseMin":24
    },
    "req":[],
    "influenceTags":[]
  },
  "Light Brigandine":{
    "implicitModTypes":[],
    "tags":[],
    "armour":[],
    "req":{
      "dex":16
    },
    "influenceTags":[]
  },
  "Scale Doublet":{
    "implicitModTypes":[],
    "tags":[],
    "armour":{
      "EvasionBaseMin":97,
      "EvasionBaseMax":121
    },
    "req":[],
    "influenceTags":[]
  },
  "Infantry Brigandine":{
    "implicitModTypes":[],
    "tags":[],
    "armour":{
      "EvasionBaseMin":119,
      "EvasionBaseMax":142
    },
    "req":[],
    "influenceTags":[]
  },
  "Full Scale Armour":{
    "implicitModTypes":[],
    "tags":[],
    "armour":[],
    "req":[],
    "influenceTags":[]
  },
  "Soldier's Brigandine":{
    "implicitModTypes":[],
    "tags":[],
    "armour":{
      "EvasionBaseMax":210
    },
    "req":[],
    "influenceTags":[]
  },
  "Field Lamellar":{
    "implicitModTypes":[],
    "tags":[],
    "armour":{
      "EvasionBaseMax":223
    },
    "req":[],
    "influenceTags":[]
  },
  "Wyrmscale Doublet":{
    "implicitModTypes":[],
    "tags":[],
    "armour":{
      "EvasionBaseMax":236
    },
    "req":{
      "dex":57
    },
    "influenceTags":[]
  },
  "Hussar Brigandine":{
    "implicitModTypes":[],
    "tags":[],
    "armour":{
      "EvasionBaseMin":232,
      "EvasionBaseMax":278
    },
    "req":{
      "level":42
    },
    "influenceTags":[]
  },
  "Full Wyrmscale":{
    "implicitModTypes":[],
    "tags":[],
    "armour":{
      "EvasionBaseMax":292
    },
    "req":[],
    "influenceTags":[]
  },
  "Commander's Brigandine":{
    "implicitModTypes":[],
    "tags":[],
    "armour":{
      "EvasionBaseMin":275,
      "EvasionBaseMax":325
    },
    "req":{
      "level":50
    },
    "influenceTags":[]
  },
  "Battle Lamellar":{
    "implicitModTypes":[],
    "tags":[],
    "armour":{
      "EvasionBaseMin":297,
      "EvasionBaseMax":341
    },
    "req":{
      "level":54
    },
    "influenceTags":[]
  },
  "Dragonscale Doublet":{
    "implicitModTypes":[],
    "tags":[],
    "armour":{
      "EvasionBaseMin":313,
      "EvasionBaseMax":351
    },
    "req":{
      "dex":83
    },
    "influenceTags":[]
  },
  "Plate Vest":{
    "implicitModTypes":[],
    "tags":[],
    "armour":[],
    "req":{
      "str":12
    },
    "influenceTags":[]
  },
  "Full Dragonscale":{
    "implicitModTypes":[],
    "tags":[],
    "armour":{
      "ArmourBaseMax":541,
      "ArmourBaseMin":470
    },
    "req":[],
    "influenceTags":[]
  },
  "General's Brigandine":{
    "implicitModTypes":[],
    "tags":[],
    "armour":{
      "EvasionBaseMin":415,
      "EvasionBaseMax":465
    },
    "req":[],
    "influenceTags":[]
  },
  "Triumphant Lamellar":{
    "implicitModTypes":[],
    "tags":[],
    "armour":{
      "EvasionBaseMin":477,
      "EvasionBaseMax":549,
      "ArmourBaseMax":437,
      "ArmourBaseMin":380
    },
    "req":{
      "dex":116,
      "str":95
    },
    "influenceTags":[]
  },
  "Full Wyvernscale":{
    "implicitModTypes":[],
    "tags":[],
    "armour":[],
    "req":[],
    "influenceTags":[]
  },
  "Marshall's Brigandine":{
    "implicitModTypes":[],
    "tags":[],
    "armour":[],
    "req":[],
    "influenceTags":[]
  },
  "Conquest Lamellar":{
    "implicitModTypes":[],
    "tags":[],
    "armour":[],
    "req":[],
    "influenceTags":[]
  },
  "Chainmail Vest":{
    "implicitModTypes":[],
    "tags":[],
    "armour":[],
    "req":[],
    "influenceTags":[]
  },
  "Oiled Vest":{
    "implicitModTypes":[],
    "tags":[],
    "armour":[],
    "req":[],
    "influenceTags":[]
  },
  "Desert Brigandine":{
    "implicitModTypes":[],
    "tags":[],
    "armour":{
      "EvasionBaseMin":376
    },
    "req":[],
    "influenceTags":[]
  },
  "Chainmail Tunic":{
    "implicitModTypes":[],
    "tags":[],
    "armour":[],
    "req":[],
    "influenceTags":[]
  },
  "Ringmail Coat":{
    "implicitModTypes":[],
    "tags":[],
    "armour":[],
    "req":[],
    "influenceTags":[]
  },
  "Chainmail Doublet":{
    "implicitModTypes":[],
    "tags":[],
    "armour":{
      "ArmourBaseMax":140,
      "EnergyShieldBaseMax":31
    },
    "req":[],
    "influenceTags":[]
  },
  "Full Ringmail":{
    "implicitModTypes":[],
    "tags":[],
    "armour":[],
    "req":[],
    "influenceTags":[]
  },
  "Full Chainmail":{
    "implicitModTypes":[],
    "tags":[],
    "armour":{
      "ArmourBaseMax":199
    },
    "req":[],
    "influenceTags":[]
  },
  "Holy Chainmail":{
    "implicitModTypes":[],
    "tags":[],
    "armour":[],
    "req":[],
    "influenceTags":[]
  },
  "Latticed Ringmail":{
    "implicitModTypes":[],
    "tags":[],
    "armour":[],
    "req":[],
    "influenceTags":[]
  },
  "Crusader Chainmail":{
    "implicitModTypes":[],
    "tags":[],
    "armour":{
      "ArmourBaseMin":237,
      "ArmourBaseMax":266
    },
    "req":[],
    "influenceTags":[]
  },
  "Ornate Ringmail":{
    "implicitModTypes":[],
    "tags":[],
    "armour":{
      "ArmourBaseMin":259,
      "ArmourBaseMax":298
    },
    "req":{
      "level":47
    },
    "influenceTags":[]
  },
  "Chain Hauberk":{
    "implicitModTypes":[],
    "tags":[],
    "armour":{
      "ArmourBaseMin":281,
      "ArmourBaseMax":314,
      "EnergyShieldBaseMin":58
    },
    "req":[],
    "influenceTags":[]
  },
  "Devout Chainmail":{
    "implicitModTypes":[],
    "tags":[],
    "armour":{
      "ArmourBaseMax":363,
      "EnergyShieldBaseMax":74
    },
    "req":[],
    "influenceTags":[]
  },
  "Loricated Ringmail":{
    "implicitModTypes":[],
    "tags":[],
    "armour":{
      "ArmourBaseMax":374
    },
    "req":[],
    "influenceTags":[]
  },
  "Conquest Chainmail":{
    "implicitModTypes":[],
    "tags":[],
    "armour":{
      "ArmourBaseMax":445
    },
    "req":{
      "level":61
    },
    "influenceTags":[]
  },
  "Elegant Ringmail":{
    "implicitModTypes":[],
    "tags":[],
    "armour":{
      "ArmourBaseMin":377,
      "ArmourBaseMax":433,
      "EnergyShieldBaseMin":92
    },
    "req":[],
    "influenceTags":[]
  },
  "Saint's Hauberk":{
    "implicitModTypes":[],
    "tags":[],
    "armour":{
      "ArmourBaseMin":443,
      "ArmourBaseMax":496,
      "EnergyShieldBaseMax":85
    },
    "req":[],
    "influenceTags":[]
  },
  "Saintly Chainmail":{
    "implicitModTypes":[],
    "tags":[],
    "armour":{
      "ArmourBaseMin":401,
      "ArmourBaseMax":461
    },
    "req":[],
    "influenceTags":[]
  }
}