{
  "Dragonscale Doublet":{
    "socketLimit":6,
    "tags":{
      "str_dex_armour":true
    },
    "req":{
      "level":57,
      "str":83
    },
    "armour":{
      "ArmourBaseMin":313,
      "EvasionBaseMax":351,
      "MovementPenalty":3
    },
    "implicitModTypes":[],
    "influenceTags":{
      "tangle":"body_armour_tangle",
      "elder":"body_armour_elder",
      "cleansing":"body_armour_cleansing",
      "adjudicator":"body_armour_adjudicator",
      "eyrie":"body_armour_eyrie",
      "basilisk":"body_armour_basilisk",
      "crusader":"body_armour_crusader",
      "shaper":"body_armour_shaper"
    },
    "subType":"Armour/Evasion",
    "type":"Body Armour"
  },
  "Desert Brigandine":{
    "tags":[],
    "req":{
      "level":60,
      "str":96
    },
    "armour":{
      "ArmourBaseMin":376,
      "EvasionBaseMax":451
    },
    "implicitModTypes":[],
    "influenceTags":[]
  },
  "Full Dragonscale":{
    "tags":[],
    "req":{
      "level":63,
      "str":115,
      "dex":94
    },
    "armour":{
      "ArmourBaseMin":470,
      "EvasionBaseMax":429,
      "EvasionBaseMin":373,
      "ArmourBaseMax":541
    },
    "implicitModTypes":[],
    "influenceTags":[]
  },
  "General's Brigandine":{
    "tags":[],
    "req":{
      "level":66,
      "str":103
    },
    "armour":{
      "ArmourBaseMin":415,
      "EvasionBaseMax":465
    },
    "implicitModTypes":[],
    "influenceTags":[]
  },
  "Triumphant Lamellar":{
    "tags":[],
    "req":{
      "level":69,
      "str":95,
      "dex":116
    },
    "armour":{
      "ArmourBaseMin":380,
      "EvasionBaseMax":549,
      "EvasionBaseMin":477,
      "ArmourBaseMax":437
    },
    "implicitModTypes":[],
    "influenceTags":[]
  },
  "Full Wyvernscale":{
    "tags":[],
    "req":{
      "level":73,
      "str":133
    },
    "armour":{
      "ArmourBaseMin":545,
      "EvasionBaseMax":627
    },
    "implicitModTypes":[],
    "influenceTags":[]
  },
  "Marshall's Brigandine":{
    "tags":[],
    "req":{
      "level":78,
      "str":151
    },
    "armour":{
      "EvasionBaseMax":721
    },
    "implicitModTypes":[],
    "influenceTags":[]
  },
  "Conquest Lamellar":{
    "tags":[],
    "req":{
      "level":84,
      "str":173
    },
    "armour":{
      "ArmourBaseMin":723,
      "EvasionBaseMax":831
    },
    "implicitModTypes":[],
    "influenceTags":[]
  },
  "Chainmail Vest":{
    "tags":[],
    "req":{
      "int":10
    },
    "armour":{
      "ArmourBaseMin":27,
      "EnergyShieldBaseMax":13,
      "EnergyShieldBaseMin":9,
      "ArmourBaseMax":38,
      "MovementPenalty":5
    },
    "implicitModTypes":[],
    "influenceTags":[],
    "subType":"Armour/Energy Shield"
  },
  "Chainmail Tunic":{
    "tags":[],
    "req":{
      "level":8,
      "str":16
    },
    "armour":{
      "ArmourBaseMin":48,
      "EnergyShieldBaseMax":17
    },
    "implicitModTypes":[],
    "influenceTags":[]
  },
  "Ringmail Coat":{
    "tags":[],
    "req":{
      "str":28
    },
    "armour":{
      "ArmourBaseMin":97,
      "EnergyShieldBaseMin":22,
      "ArmourBaseMax":121
    },
    "implicitModTypes":[],
    "influenceTags":[]
  },
  "Chainmail Doublet":{
    "tags":[],
    "req":{
      "level":21,
      "str":34
    },
    "armour":{
      "ArmourBaseMin":119,
      "EnergyShieldBaseMax":31,
      "ArmourBaseMax":140
    },
    "implicitModTypes":[],
    "influenceTags":[]
  },
  "Full Ringmail":{
    "tags":[],
    "req":{
      "str":43
    },
    "armour":{
      "ArmourBaseMin":156,
      "EnergyShieldBaseMax":39,
      "ArmourBaseMax":180
    },
    "implicitModTypes":[],
    "influenceTags":[]
  },
  "Full Chainmail":{
    "tags":[],
    "req":{
      "level":32
    },
    "armour":{
      "ArmourBaseMin":178,
      "ArmourBaseMax":199
    },
    "implicitModTypes":[],
    "influenceTags":[]
  },
  "Holy Chainmail":{
    "tags":[],
    "req":{
      "level":35,
      "str":53
    },
    "armour":{
      "ArmourBaseMin":194,
      "EnergyShieldBaseMax":49,
      "EnergyShieldBaseMin":41,
      "ArmourBaseMax":233
    },
    "implicitModTypes":[],
    "influenceTags":[]
  },
  "Latticed Ringmail":{
    "tags":[],
    "req":{
      "str":59
    },
    "armour":{
      "ArmourBaseMin":216,
      "EnergyShieldBaseMax":52,
      "EnergyShieldBaseMin":45,
      "ArmourBaseMax":248
    },
    "implicitModTypes":[],
    "influenceTags":[]
  },
  "Crusader Chainmail":{
    "tags":[],
    "req":{
      "str":64
    },
    "armour":{
      "ArmourBaseMin":237,
      "EnergyShieldBaseMax":55,
      "EnergyShieldBaseMin":50,
      "ArmourBaseMax":266
    },
    "implicitModTypes":[],
    "influenceTags":[]
  },
  "Ornate Ringmail":{
    "tags":[],
    "req":{
      "level":47
    },
    "armour":{
      "ArmourBaseMin":259,
      "EnergyShieldBaseMax":62,
      "EnergyShieldBaseMin":54,
      "ArmourBaseMax":298
    },
    "implicitModTypes":[],
    "influenceTags":[]
  },
  "Chain Hauberk":{
    "tags":[],
    "req":{
      "level":51,
      "str":75
    },
    "armour":{
      "ArmourBaseMin":281,
      "EnergyShieldBaseMax":65,
      "EnergyShieldBaseMin":58,
      "ArmourBaseMax":314
    },
    "implicitModTypes":[],
    "influenceTags":[]
  },
  "Devout Chainmail":{
    "tags":[],
    "req":{
      "str":80
    },
    "armour":{
      "ArmourBaseMin":302,
      "EnergyShieldBaseMax":74,
      "ArmourBaseMax":363
    },
    "implicitModTypes":[],
    "influenceTags":[]
  },
  "Loricated Ringmail":{
    "tags":[],
    "req":[],
    "armour":{
      "ArmourBaseMin":325,
      "EnergyShieldBaseMax":76,
      "ArmourBaseMax":374
    },
    "implicitModTypes":[],
    "influenceTags":[]
  },
  "Conquest Chainmail":{
    "tags":[],
    "req":{
      "level":61
    },
    "armour":{
      "ArmourBaseMin":387,
      "EnergyShieldBaseMax":91,
      "EnergyShieldBaseMin":79,
      "ArmourBaseMax":445
    },
    "implicitModTypes":[],
    "influenceTags":[]
  },
  "Elegant Ringmail":{
    "tags":[],
    "req":{
      "str":90,
      "int":105
    },
    "armour":{
      "ArmourBaseMin":377,
      "EnergyShieldBaseMin":92,
      "ArmourBaseMax":433
    },
    "implicitModTypes":[],
    "influenceTags":[]
  },
  "Saint's Hauberk":{
    "tags":[],
    "req":{
      "level":67,
      "str":109
    },
    "armour":{
      "ArmourBaseMin":443,
      "EnergyShieldBaseMax":85,
      "ArmourBaseMax":496
    },
    "implicitModTypes":[],
    "influenceTags":[]
  },
  "Saintly Chainmail":{
    "tags":[],
    "req":{
      "level":70,
      "str":99
    },
    "armour":{
      "ArmourBaseMin":401,
      "EnergyShieldBaseMax":110,
      "ArmourBaseMax":461
    },
    "implicitModTypes":[],
    "influenceTags":[]
  },
  "Grand Ringmail":{
    "tags":[],
    "req":[],
    "armour":{
      "EnergyShieldBaseMax":127
    },
    "implicitModTypes":[],
    "influenceTags":[]
  },
  "Plate Vest":{
    "tags":[],
    "req":{
      "str":12
    },
    "armour":{
      "ArmourBaseMin":19
    },
    "implicitModTypes":[],
    "influenceTags":[],
    "subType":"Armour"
  },
  "Sacred Chainmail":{
    "tags":[],
    "req":[],
    "armour":{
      "EnergyShieldBaseMax":167,
      "EnergyShieldBaseMin":145
    },
    "implicitModTypes":[],
    "influenceTags":[]
  },
  "Padded Vest":{
    "tags":[],
    "req":[],
    "armour":[],
    "implicitModTypes":[],
    "influenceTags":[],
    "subType":"Evasion/Energy Shield"
  },
  "Chestplate":{
    "tags":[],
    "req":{
      "str":25
    },
    "armour":{
      "ArmourBaseMin":68,
      "ArmourBaseMax":89
    },
    "implicitModTypes":[],
    "influenceTags":[]
  },
  "Copper Plate":{
    "tags":[],
    "req":[],
    "armour":{
      "ArmourBaseMin":176,
      "ArmourBaseMax":221
    },
    "implicitModTypes":[],
    "influenceTags":[]
  },
  "War Plate":{
    "tags":[],
    "req":[],
    "armour":[],
    "implicitModTypes":[],
    "influenceTags":[]
  },
  "Full Plate":{
    "tags":[],
    "req":{
      "str":81
    },
    "armour":{
      "ArmourBaseMin":284,
      "ArmourBaseMax":319
    },
    "implicitModTypes":[],
    "influenceTags":[]
  },
  "Arena Plate":{
    "tags":[],
    "req":[],
    "armour":{
      "ArmourBaseMin":324,
      "ArmourBaseMax":389
    },
    "implicitModTypes":[],
    "influenceTags":[]
  },
  "Lordly Plate":{
    "tags":[],
    "req":[],
    "armour":{
      "ArmourBaseMin":353,
      "ArmourBaseMax":417
    },
    "implicitModTypes":[],
    "influenceTags":[]
  },
  "Bronze Plate":{
    "tags":[],
    "req":{
      "level":37,
      "str":104
    },
    "armour":[],
    "implicitModTypes":[],
    "influenceTags":[]
  },
  "Battle Plate":{
    "tags":[],
    "req":{
      "str":114
    },
    "armour":{
      "ArmourBaseMin":412,
      "ArmourBaseMax":474
    },
    "implicitModTypes":[],
    "influenceTags":[]
  },
  "Sun Plate":{
    "tags":[],
    "req":{
      "str":124
    },
    "armour":{
      "ArmourBaseMax":506
    },
    "implicitModTypes":[],
    "influenceTags":[]
  },
  "Colosseum Plate":{
    "tags":[],
    "req":{
      "str":134
    },
    "armour":{
      "ArmourBaseMin":491,
      "ArmourBaseMax":589
    },
    "implicitModTypes":[],
    "influenceTags":[]
  },
  "Majestic Plate":{
    "tags":[],
    "req":[],
    "armour":{
      "ArmourBaseMin":530,
      "ArmourBaseMax":625
    },
    "implicitModTypes":[],
    "influenceTags":[]
  },
  "Golden Plate":{
    "tags":[],
    "req":{
      "level":56,
      "str":152
    },
    "armour":{
      "ArmourBaseMin":559,
      "ArmourBaseMax":643
    },
    "implicitModTypes":[],
    "influenceTags":[]
  },
  "Crusader Plate":{
    "tags":[],
    "req":{
      "str":160
    },
    "armour":{
      "ArmourBaseMin":601,
      "ArmourBaseMax":691
    },
    "implicitModTypes":[],
    "influenceTags":[]
  },
  "Astral Plate":{
    "tags":[],
    "armour":{
      "ArmourBaseMin":711,
      "ArmourBaseMax":782
    },
    "influenceTags":[],
    "implicitModTypes":[["elemental","resistance"]],
    "req":[],
    "implicit":"+(8-12)% to all Elemental Resistances"
  },
  "Golden Mantle":{
    "tags":[],
    "armour":{
      "ArmourBaseMax":86
    },
    "influenceTags":[],
    "implicitModTypes":[[]],
    "req":{
      "level":20
    },
    "subType":"Armour/Evasion/Energy Shield",
    "implicit":"+(15-25)% to all Elemental Resistances"
  },
  "Grasping Mail":{
    "tags":[],
    "req":[],
    "armour":{
      "ArmourBaseMin":217,
      "EvasionBaseMax":250,
      "EnergyShieldBaseMin":44
    },
    "implicitModTypes":[],
    "influenceTags":[]
  },
  "Sacrificial Garb":{
    "tags":[],
    "armour":{
      "ArmourBaseMin":329,
      "EnergyShieldBaseMax":77,
      "EvasionBaseMax":378
    },
    "influenceTags":[],
    "implicitModTypes":[["gem"]],
    "req":{
      "level":72
    },
    "implicit":"+1 to Level of all Vaal Skill Gems"
  },
  "Necrotic Armour":{
    "tags":[],
    "req":[],
    "armour":[],
    "implicitModTypes":[],
    "influenceTags":[]
  },
  "Gladiator Plate":{
    "tags":[],
    "req":{
      "str":177
    },
    "armour":{
      "ArmourBaseMin":738,
      "ArmourBaseMax":848
    },
    "implicitModTypes":[],
    "influenceTags":[]
  },
  "Glorious Plate":{
    "tags":[],
    "req":{
      "str":191
    },
    "armour":{
      "ArmourBaseMin":776,
      "ArmourBaseMax":892
    },
    "implicitModTypes":[],
    "influenceTags":[]
  },
  "Titan Plate":{
    "tags":[],
    "req":{
      "str":222
    },
    "armour":{
      "ArmourBaseMin":877,
      "ArmourBaseMax":1009
    },
    "implicitModTypes":[],
    "influenceTags":[]
  },
  "Torturer Garb":{
    "tags":[],
    "req":[],
    "armour":{
      "EnergyShieldBaseMin":126
    },
    "implicitModTypes":[],
    "influenceTags":[]
  },
  "Legion Plate":{
    "tags":[],
    "req":{
      "str":254
    },
    "armour":{
      "ArmourBaseMin":1018,
      "ArmourBaseMax":1171
    },
    "implicitModTypes":[],
    "influenceTags":[]
  },
  "Royal Plate":{
    "tags":[],
    "req":{
      "str":293
    },
    "armour":{
      "ArmourBaseMin":1183,
      "ArmourBaseMax":1360
    },
    "implicitModTypes":[],
    "influenceTags":[]
  },
  "Shabby Jerkin":{
    "tags":[],
    "req":{
      "dex":14
    },
    "armour":{
      "EvasionBaseMin":29
    },
    "implicitModTypes":[],
    "influenceTags":[],
    "subType":"Evasion"
  },
  "Sanguine Raiment":{
    "tags":[],
    "req":[],
    "armour":[],
    "implicitModTypes":[],
    "influenceTags":[]
  },
  "Carnal Armour":{
    "tags":[],
    "armour":{
      "EnergyShieldBaseMax":113,
      "EvasionBaseMax":388
    },
    "influenceTags":[],
    "implicitModTypes":[["resource","mana"]],
    "req":{
      "level":71,
      "int":122,
      "dex":88
    },
    "implicit":"+(20-25) to maximum Mana"
  },
  "Sadist Garb":{
    "tags":[],
    "req":[],
    "armour":{
      "EnergyShieldBaseMin":93,
      "EnergyShieldBaseMax":107,
      "EvasionBaseMin":427
    },
    "implicitModTypes":[],
    "influenceTags":[]
  },
  "Blood Raiment":{
    "tags":[],
    "req":[],
    "armour":{
      "EvasionBaseMin":436,
      "EvasionBaseMax":501
    },
    "implicitModTypes":[],
    "influenceTags":[]
  },
  "Varnished Coat":{
    "tags":[],
    "req":[],
    "armour":{
      "EvasionBaseMax":434
    },
    "implicitModTypes":[],
    "influenceTags":[]
  },
  "Strapped Leather":{
    "tags":[],
    "req":[],
    "armour":{
      "EvasionBaseMin":98
    },
    "implicitModTypes":[],
    "influenceTags":[]
  },
  "Buckskin Tunic":{
    "tags":[],
    "req":[],
    "armour":[],
    "implicitModTypes":[],
    "influenceTags":[]
  },
  "Wild Leather":{
    "tags":[],
    "req":[],
    "armour":{
      "EvasionBaseMin":255,
      "EvasionBaseMax":306
    },
    "implicitModTypes":[],
    "influenceTags":[]
  },
  "Full Leather":{
    "tags":[],
    "req":[],
    "armour":{
      "EvasionBaseMax":327
    },
    "implicitModTypes":[],
    "influenceTags":[]
  },
  "Sun Leather":{
    "tags":[],
    "req":[],
    "armour":{
      "EvasionBaseMax":382
    },
    "implicitModTypes":[],
    "influenceTags":[]
  },
  "Thief's Garb":{
    "tags":[],
    "req":[],
    "armour":{
      "EvasionBaseMax":396
    },
    "implicitModTypes":[],
    "influenceTags":[]
  },
  "Eelskin Tunic":{
    "tags":[],
    "req":[],
    "armour":[],
    "implicitModTypes":[],
    "influenceTags":[]
  },
  "Frontier Leather":{
    "tags":[],
    "req":[],
    "armour":{
      "EvasionBaseMax":495
    },
    "implicitModTypes":[],
    "influenceTags":[]
  },
  "Glorious Leather":{
    "tags":[],
    "req":[],
    "armour":{
      "EvasionBaseMax":519
    },
    "implicitModTypes":[],
    "influenceTags":[]
  },
  "Coronal Leather":{
    "tags":[],
    "req":[],
    "armour":{
      "EvasionBaseMax":579
    },
    "implicitModTypes":[],
    "influenceTags":[]
  },
  "Cutthroat's Garb":{
    "tags":[],
    "req":[],
    "armour":{
      "EvasionBaseMax":594
    },
    "implicitModTypes":[],
    "influenceTags":[]
  },
  "Sharkskin Tunic":{
    "tags":[],
    "req":[],
    "armour":[],
    "implicitModTypes":[],
    "influenceTags":[]
  },
  "Destiny Leather":{
    "tags":[],
    "req":[],
    "armour":[],
    "implicitModTypes":[],
    "influenceTags":[]
  },
  "Exquisite Leather":{
    "tags":[],
    "req":{
      "dex":170
    },
    "armour":{
      "EvasionBaseMin":704,
      "EvasionBaseMax":810
    },
    "implicitModTypes":[],
    "influenceTags":[]
  },
  "Zodiac Leather":{
    "tags":[],
    "req":{
      "dex":197
    },
    "armour":{
      "EvasionBaseMin":854,
      "EvasionBaseMax":982
    },
    "implicitModTypes":[],
    "influenceTags":[]
  },
  "Assassin's Garb":{
    "tags":[],
    "armour":{
      "EvasionBaseMax":811,
      "EvasionBaseMin":737
    },
    "influenceTags":[],
    "implicitModTypes":[["speed"]],
    "req":{
      "dex":183
    },
    "implicit":"3% increased Movement Speed"
  },
  "Sentinel Jacket":{
    "tags":[],
    "req":[],
    "armour":{
      "EvasionBaseMin":330,
      "EvasionBaseMax":370
    },
    "implicitModTypes":[],
    "influenceTags":[]
  },
  "Crypt Armour":{
    "tags":[],
    "req":{
      "int":82
    },
    "armour":{
      "EvasionBaseMin":308,
      "EvasionBaseMax":369
    },
    "implicitModTypes":[],
    "influenceTags":[]
  },
  "Supreme Leather":{
    "tags":[],
    "req":[],
    "armour":{
      "EvasionBaseMin":894,
      "EvasionBaseMax":1028
    },
    "implicitModTypes":[],
    "influenceTags":[]
  },
  "Astral Leather":{
    "tags":[],
    "req":[],
    "armour":{
      "EvasionBaseMin":1037,
      "EvasionBaseMax":1193
    },
    "implicitModTypes":[],
    "influenceTags":[]
  },
  "Syndicate's Garb":{
    "tags":[],
    "req":[],
    "armour":{
      "EvasionBaseMin":1205,
      "EvasionBaseMax":1386
    },
    "implicitModTypes":[],
    "influenceTags":[]
  },
  "Simple Robe":{
    "tags":[],
    "req":[],
    "armour":[],
    "implicitModTypes":[],
    "influenceTags":[],
    "subType":"Energy Shield"
  },
  "Lacquered Garb":{
    "tags":[],
    "req":[],
    "armour":{
      "EvasionBaseMin":286
    },
    "implicitModTypes":[],
    "influenceTags":[]
  },
  "Crimson Raiment":{
    "tags":[],
    "req":[],
    "armour":{
      "EvasionBaseMin":264,
      "EvasionBaseMax":304
    },
    "implicitModTypes":[],
    "influenceTags":[]
  },
  "Sleek Coat":{
    "tags":[],
    "req":[],
    "armour":{
      "EvasionBaseMin":243,
      "EvasionBaseMax":287
    },
    "implicitModTypes":[],
    "influenceTags":[]
  },
  "Quilted Jacket":{
    "tags":[],
    "req":{
      "level":40
    },
    "armour":{
      "EnergyShieldBaseMin":46
    },
    "implicitModTypes":[],
    "influenceTags":[]
  },
  "Bone Armour":{
    "tags":[],
    "req":[],
    "armour":[],
    "implicitModTypes":[],
    "influenceTags":[]
  },
  "Silken Vest":{
    "tags":[],
    "req":{
      "level":11
    },
    "armour":{
      "EnergyShieldBaseMin":30
    },
    "implicitModTypes":[],
    "influenceTags":[]
  },
  "Scholar's Robe":{
    "tags":[],
    "req":{
      "level":18
    },
    "armour":[],
    "implicitModTypes":[],
    "influenceTags":[]
  },
  "Silken Garb":{
    "tags":[],
    "req":[],
    "armour":[],
    "implicitModTypes":[],
    "influenceTags":[]
  },
  "Mage's Vestment":{
    "tags":[],
    "req":[],
    "armour":[],
    "implicitModTypes":[],
    "influenceTags":[]
  },
  "Silk Robe":{
    "tags":[],
    "req":[],
    "armour":[],
    "implicitModTypes":[],
    "influenceTags":[]
  },
  "Cabalist Regalia":{
    "tags":[],
    "req":[],
    "armour":[],
    "implicitModTypes":[],
    "influenceTags":[]
  },
  "Sage's Robe":{
    "tags":[],
    "req":[],
    "armour":[],
    "implicitModTypes":[],
    "influenceTags":[]
  },
  "Silken Wrap":{
    "tags":[],
    "req":[],
    "armour":[],
    "implicitModTypes":[],
    "influenceTags":[]
  },
  "Conjurer's Vestment":{
    "tags":[],
    "req":[],
    "armour":[],
    "implicitModTypes":[],
    "influenceTags":[]
  },
  "Spidersilk Robe":{
    "tags":[],
    "req":[],
    "armour":{
      "EnergyShieldBaseMin":101,
      "EnergyShieldBaseMax":117
    },
    "implicitModTypes":[],
    "influenceTags":[]
  },
  "Destroyer Regalia":{
    "tags":[],
    "req":[],
    "armour":{
      "EnergyShieldBaseMax":129
    },
    "implicitModTypes":[],
    "influenceTags":[]
  },
  "Savant's Robe":{
    "tags":[],
    "req":[],
    "armour":{
      "EnergyShieldBaseMax":132
    },
    "implicitModTypes":[],
    "influenceTags":[]
  },
  "Necromancer Silks":{
    "tags":[],
    "req":[],
    "armour":{
      "EnergyShieldBaseMin":123,
      "EnergyShieldBaseMax":147
    },
    "implicitModTypes":[],
    "influenceTags":[]
  },
  "Occultist's Vestment":{
    "tags":[],
    "armour":{
      "EnergyShieldBaseMin":137
    },
    "influenceTags":[],
    "implicitModTypes":[["caster_damage","damage","caster"]],
    "req":[],
    "implicit":"(3-10)% increased Spell Damage"
  },
  "Paladin's Hauberk":{
    "tags":[],
    "req":[],
    "armour":[],
    "implicitModTypes":[],
    "influenceTags":[]
  },
  "Oiled Vest":{
    "tags":[],
    "req":[],
    "armour":[],
    "implicitModTypes":[],
    "influenceTags":[]
  },
  "Oiled Coat":{
    "tags":[],
    "req":[],
    "armour":{
      "EnergyShieldBaseMax":33,
      "EvasionBaseMax":146
    },
    "implicitModTypes":[],
    "influenceTags":[]
  },
  "Padded Jacket":{
    "tags":[],
    "req":[],
    "armour":{
      "EnergyShieldBaseMin":24,
      "EvasionBaseMin":102,
      "EvasionBaseMax":128
    },
    "implicitModTypes":[],
    "influenceTags":[]
  },
  "Widowsilk Robe":{
    "tags":[],
    "req":{
      "int":187
    },
    "armour":{
      "EnergyShieldBaseMin":157,
      "EnergyShieldBaseMax":181
    },
    "implicitModTypes":[],
    "influenceTags":[]
  },
  "Vaal Regalia":{
    "tags":[],
    "req":[],
    "armour":{
      "EnergyShieldBaseMin":171
    },
    "implicitModTypes":[],
    "influenceTags":[]
  },
  "Arcane Vestment":{
    "tags":[],
    "req":[],
    "armour":{
      "EnergyShieldBaseMin":196,
      "EnergyShieldBaseMax":225
    },
    "implicitModTypes":[],
    "influenceTags":[]
  },
  "Nightweave Robe":{
    "tags":[],
    "req":[],
    "armour":{
      "EnergyShieldBaseMin":227,
      "EnergyShieldBaseMax":260
    },
    "implicitModTypes":[],
    "influenceTags":[]
  },
  "Twilight Regalia":{
    "tags":[],
    "req":[],
    "armour":{
      "EnergyShieldBaseMin":262
    },
    "implicitModTypes":[],
    "influenceTags":[]
  },
  "Scale Vest":{
    "tags":[],
    "req":[],
    "armour":[],
    "implicitModTypes":[],
    "influenceTags":[]
  },
  "Scarlet Raiment":{
    "tags":[],
    "req":[],
    "armour":[],
    "implicitModTypes":[],
    "influenceTags":[]
  },
  "Waxed Garb":{
    "tags":[],
    "req":[],
    "armour":{
      "EvasionBaseMax":205
    },
    "implicitModTypes":[],
    "influenceTags":[]
  },
  "Light Brigandine":{
    "tags":[],
    "req":[],
    "armour":[],
    "implicitModTypes":[],
    "influenceTags":[]
  },
  "Scale Doublet":{
    "tags":[],
    "req":[],
    "armour":[],
    "implicitModTypes":[],
    "influenceTags":[]
  },
  "Infantry Brigandine":{
    "tags":[],
    "req":[],
    "armour":{
      "EvasionBaseMax":142
    },
    "implicitModTypes":[],
    "influenceTags":[]
  },
  "Full Scale Armour":{
    "tags":[],
    "req":[],
    "armour":[],
    "implicitModTypes":[],
    "influenceTags":[]
  },
  "Soldier's Brigandine":{
    "tags":[],
    "req":[],
    "armour":{
      "EvasionBaseMax":210
    },
    "implicitModTypes":[],
    "influenceTags":[]
  },
  "Field Lamellar":{
    "tags":[],
    "req":[],
    "armour":{
      "EvasionBaseMax":223
    },
    "implicitModTypes":[],
    "influenceTags":[]
  },
  "Wyrmscale Doublet":{
    "tags":[],
    "req":[],
    "armour":{
      "EvasionBaseMax":236
    },
    "implicitModTypes":[],
    "influenceTags":[]
  },
  "Hussar Brigandine":{
    "tags":[],
    "req":{
      "level":42
    },
    "armour":{
      "ArmourBaseMin":232,
      "EvasionBaseMax":278
    },
    "implicitModTypes":[],
    "influenceTags":[]
  },
  "Full Wyrmscale":{
    "tags":[],
    "req":[],
    "armour":{
      "EvasionBaseMax":292
    },
    "implicitModTypes":[],
    "influenceTags":[]
  },
  "Commander's Brigandine":{
    "tags":[],
    "req":[],
    "armour":{
      "ArmourBaseMin":275
    },
    "implicitModTypes":[],
    "influenceTags":[]
  },
  "Battle Lamellar":{
    "tags":[],
    "req":[],
    "armour":{
      "ArmourBaseMin":297,
      "EvasionBaseMax":341
    },
    "implicitModTypes":[],
    "influenceTags":[]
  }
}