{
  "FlaskChillFreezeImmunity3":{
    "1":"Grants Immunity to Chill for (12-14) seconds if used while Chilled",
    "2":"Grants Immunity to Freeze for (12-14) seconds if used while Frozen",
    "level":52,
    "type":"Suffix",
    "weightVal":[0,750],
    "modTags":["flask"],
    "statOrder":[783,783.1],
    "group":"FlaskChillFreezeImmunity",
    "affix":"of Entropy",
    "weightKey":["utility_flask","default"]
  },
  "FlaskBuffMovementSpeedWhileHealing":{
    "1":"(6-8)% increased Movement Speed during Effect",
    "level":5,
    "weightVal":[1000],
    "modTags":[null,"speed"],
    "statOrder":[826],
    "group":"FlaskBuffMovementSpeedWhileHealing",
    "affix":"of the Hare",
    "weightKey":[]
  },
  "FlaskChillFreezeImmunity4":{
    "1":"Grants Immunity to Chill for (15-17) seconds if used while Chilled",
    "2":"Grants Immunity to Freeze for (15-17) seconds if used while Frozen",
    "level":76,
    "weightVal":[],
    "modTags":[],
    "statOrder":[],
    "affix":"of Thawing",
    "weightKey":[]
  },
  "FlaskBuffMovementSpeedWhileHealing2":{
    "1":"(9-11)% increased Movement Speed during Effect",
    "level":65,
    "weightVal":[],
    "modTags":[],
    "statOrder":[],
    "affix":"of the Lynx",
    "weightKey":[]
  },
  "FlaskBuffMovementSpeedWhileHealing3":{
    "1":"(12-14)% increased Movement Speed during Effect",
    "level":85,
    "weightVal":[],
    "modTags":[],
    "statOrder":[],
    "affix":"of the Cheetah",
    "weightKey":[]
  },
  "FlaskBuffStunRecoveryWhileHealing":{
    "1":"(51-56)% increased Block and Stun Recovery during Effect",
    "level":1,
    "weightVal":[600],
    "modTags":[],
    "statOrder":[827],
    "group":"FlaskBuffStunRecoveryWhileHealing",
    "affix":"of Stiffness",
    "weightKey":[]
  },
  "FlaskIgniteImmunity2_":{
    "1":"Grants Immunity to Ignite for (9-11) seconds if used while Ignited",
    "2":"Removes all Burning when used",
    "level":30,
    "weightVal":[],
    "modTags":[],
    "statOrder":[785,785.1],
    "group":"FlaskIgniteImmunity",
    "affix":"of Quashing",
    "weightKey":[]
  },
  "FlaskBuffStunRecoveryWhileHealing2":{
    "1":"(57-62)% increased Block and Stun Recovery during Effect",
    "level":19,
    "weightVal":[],
    "modTags":[],
    "statOrder":[],
    "affix":"of Bracing",
    "weightKey":[]
  },
  "FlaskIgniteImmunity3_":{
    "1":"Grants Immunity to Ignite for (12-14) seconds if used while Ignited",
    "level":54,
    "weightVal":[],
    "modTags":[],
    "statOrder":[],
    "affix":"of Quelling",
    "weightKey":[]
  },
  "FlaskBuffStunRecoveryWhileHealing3":{
    "1":"(63-68)% increased Block and Stun Recovery during Effect",
    "level":37,
    "weightVal":[],
    "modTags":[],
    "statOrder":[],
    "affix":"of Ballast",
    "weightKey":[]
  },
  "FlaskIgniteImmunity4":{
    "1":"Grants Immunity to Ignite for (15-17) seconds if used while Ignited",
    "level":78,
    "weightVal":[],
    "modTags":[],
    "statOrder":[],
    "affix":"of Quenching",
    "weightKey":[]
  },
  "FlaskBuffStunRecoveryWhileHealing4":{
    "1":"(69-74)% increased Block and Stun Recovery during Effect",
    "level":55,
    "weightVal":[],
    "modTags":[],
    "statOrder":[],
    "affix":"of Counterpoise",
    "weightKey":[]
  },
  "FlaskPoisonImmunity1__":{
    "1":"Grants Immunity to Poison for (6-8) seconds if used while Poisoned",
    "level":16,
    "weightVal":[],
    "modTags":[],
    "statOrder":[789],
    "group":"FlaskPoisonImmunity",
    "affix":"of the Antitoxin",
    "weightKey":[]
  },
  "FlaskBuffStunRecoveryWhileHealing5":{
    "1":"(75-80)% increased Block and Stun Recovery during Effect",
    "level":73,
    "weightVal":[],
    "modTags":[],
    "statOrder":[],
    "affix":"of Stabilisation",
    "weightKey":[]
  },
  "FlaskBuffShockEffect1":{
    "1":"(36-41)% reduced Effect of Shock on you during Effect",
    "level":6,
    "weightVal":[],
    "modTags":[],
    "statOrder":[883],
    "group":"FlaskBuffShockEffect",
    "affix":"of the Plover",
    "weightKey":[]
  },
  "FlaskPoisonImmunity2":{
    "1":"Grants Immunity to Poison for (9-11) seconds if used while Poisoned",
    "level":38,
    "weightVal":[],
    "modTags":[],
    "statOrder":[],
    "affix":"of the Remedy",
    "weightKey":[]
  },
  "FlaskBuffResistancesWhileHealing":{
    "1":"(12-14)% additional Elemental Resistances during Effect",
    "weightVal":[],
    "modTags":[null,"elemental","resistance"],
    "statOrder":[828],
    "group":"FlaskBuffResistancesWhileHealing",
    "affix":"of the Crystal",
    "weightKey":[]
  },
  "FlaskBleedingAndCorruptedBloodImmunityDuringEffect3___":{
    "1":"(35-39)% less Duration",
    "2":"Immunity to Bleeding and Corrupted Blood during Effect",
    "weightVal":[],
    "modTags":[],
    "statOrder":[741,859],
    "group":"FlaskBleedingAndCorruptedBloodImmunityDuringEffect",
    "affix":"of the Iguana",
    "weightKey":[]
  },
  "FlaskBuffShockEffect2":{
    "1":"(42-47)% reduced Effect of Shock on you during Effect",
    "level":25,
    "weightVal":[],
    "modTags":[],
    "statOrder":[],
    "affix":"of the Sandpiper",
    "weightKey":[]
  },
  "FlaskHealsMinions4____":{
    "1":"Grants (160-179)% of Life Recovery to Minions",
    "level":64,
    "weightVal":[],
    "modTags":[null,"resource","life","minion"],
    "statOrder":[733],
    "group":"FlaskHealsMinions",
    "affix":"of the Conjurer",
    "weightKey":[null,"mana_flask"]
  },
  "FlaskBuffResistancesWhileHealing2":{
    "level":21,
    "weightVal":[],
    "modTags":[],
    "statOrder":[],
    "affix":"of the Prism",
    "weightKey":[]
  },
  "FlaskBuffShockEffect3___":{
    "1":"(48-52)% reduced Effect of Shock on you during Effect",
    "level":44,
    "weightVal":[],
    "modTags":[],
    "statOrder":[],
    "affix":"of the Cormorant",
    "weightKey":[]
  },
  "FlaskBuffResistancesWhileHealing3":{
    "1":"(15-17)% additional Elemental Resistances during Effect",
    "level":41,
    "weightVal":[],
    "modTags":[],
    "statOrder":[],
    "affix":"of the Kaleidoscope",
    "weightKey":[]
  },
  "FlaskDispellsPoison1":{
    "1":"Grants Immunity to Poison for 4 seconds if used while Poisoned",
    "weightVal":[],
    "modTags":[null,"poison","chaos","ailment"],
    "statOrder":[788],
    "group":"FlaskDispellsPoison",
    "affix":"of Curing",
    "weightKey":[]
  },
  "FlaskBuffShockEffect4":{
    "1":"(52-59)% reduced Effect of Shock on you during Effect",
    "level":63,
    "weightVal":[],
    "modTags":[],
    "statOrder":[],
    "affix":"of the Sanderling",
    "weightKey":[]
  },
  "FlaskBuffResistancesWhileHealing4":{
    "level":61,
    "weightVal":[],
    "modTags":[],
    "statOrder":[],
    "affix":"of Variegation",
    "weightKey":[]
  },
  "FlaskPoisonImmunity3":{
    "1":"Grants Immunity to Poison for (12-14) seconds if used while Poisoned",
    "level":60,
    "weightVal":[],
    "modTags":[],
    "statOrder":[],
    "affix":"of the Cure",
    "weightKey":[]
  },
  "FlaskBuffResistancesWhileHealing5_":{
    "1":"(18-20)% additional Elemental Resistances during Effect",
    "level":81,
    "weightVal":[],
    "modTags":[],
    "statOrder":[],
    "affix":"of the Rainbow",
    "weightKey":[]
  },
  "FlaskPoisonImmunityDuringEffect2":{
    "1":"(40-44)% less Duration",
    "2":"Immunity to Poison during Effect",
    "level":46,
    "weightVal":[],
    "modTags":[],
    "statOrder":[null,862],
    "group":"FlaskPoisonImmunityDuringEffect",
    "affix":"of the Hedgehog",
    "weightKey":[]
  },
  "FlaskEffectReducedDuration1":{
    "1":"(33-38)% reduced Duration",
    "2":"25% increased effect",
    "level":20,
    "type":"Prefix",
    "weightVal":[],
    "modTags":[],
    "statOrder":[740,815],
    "group":"FlaskEffectReducedDuration",
    "affix":"Abecedarian's",
    "weightKey":[]
  },
  "FlaskBuffLifeLeechWhileHealing":{
    "1":"2% of Physical Attack Damage Leeched as Life during Effect",
    "level":10,
    "weightVal":[],
    "modTags":[null,null,null,"physical","attack"],
    "statOrder":[829],
    "group":"FlaskBuffLifeLeechWhileHealing",
    "affix":"of Gluttony",
    "weightKey":[]
  },
  "FlaskPoisonImmunityDuringEffect3":{
    "weightVal":[],
    "modTags":[],
    "statOrder":[],
    "affix":"of the Opossum",
    "weightKey":[]
  },
  "FlaskPoisonImmunity4":{
    "1":"Grants Immunity to Poison for (15-17) seconds if used while Poisoned",
    "level":82,
    "weightVal":[],
    "modTags":[],
    "statOrder":[],
    "affix":"of the Antidote",
    "weightKey":[]
  },
  "FlaskBuffLifeLeechPermyriadWhileHealing":{
    "1":"0.4% of Physical Attack Damage Leeched as Life during Effect",
    "weightVal":[],
    "modTags":[],
    "statOrder":[832],
    "group":"FlaskBuffLifeLeechPermyriadWhileHealing",
    "weightKey":[]
  },
  "FlaskEffectReducedDuration2":{
    "1":"(28-32)% reduced Duration",
    "level":50,
    "weightVal":[],
    "modTags":[],
    "statOrder":[],
    "affix":"Dabbler's",
    "weightKey":[]
  },
  "FlaskBuffManaLeechPermyriadWhileHealing":{
    "1":"0.4% of Physical Attack Damage Leeched as Mana during Effect",
    "level":12,
    "weightVal":[],
    "modTags":[null,null,"mana"],
    "statOrder":[834],
    "group":"FlaskBuffManaLeechPermyriadWhileHealing",
    "affix":"of Craving",
    "weightKey":[]
  },
  "FlaskIgniteImmunityDuringEffect2":{
    "2":"Immunity to Ignite during Effect",
    "3":"Removes Burning on use",
    "level":40,
    "affix":"of the Mussel",
    "weightVal":[],
    "modTags":[],
    "statOrder":[null,796,796.1],
    "group":"FlaskIgniteImmunityDuringEffect",
    "weightKey":[]
  },
  "FlaskEffectReducedDuration3":{
    "1":"(23-27)% reduced Duration",
    "level":80,
    "weightVal":[],
    "modTags":[],
    "statOrder":[],
    "affix":"Alchemist's",
    "weightKey":[]
  },
  "FlaskBuffKnockbackWhileHealing":{
    "1":"Adds Knockback to Melee Attacks during Effect",
    "level":9,
    "weightVal":[],
    "modTags":[],
    "statOrder":[835],
    "group":"FlaskBuffKnockbackWhileHealing",
    "affix":"of Fending",
    "weightKey":[]
  },
  "FlaskShockImmunityDuringEffect3":{
    "2":"Immunity to Shock during Effect",
    "level":74,
    "weightVal":[],
    "modTags":[],
    "statOrder":[null,863],
    "group":"FlaskShockImmunityDuringEffect",
    "affix":"of the Eel",
    "weightKey":[]
  },
  "FlaskChargesUsed1":{
    "1":"(14-16)% reduced Charges per use",
    "level":14,
    "weightVal":[],
    "modTags":[],
    "statOrder":[729],
    "group":"FlaskChargesUsed",
    "affix":"Apprentice's",
    "weightKey":[]
  },
  "FlaskFreezeAndChillImmunityDuringEffect":{
    "1":"(45-49)% less Duration",
    "2":"Immunity to Freeze and Chill during Effect",
    "level":4,
    "weightVal":[],
    "modTags":[],
    "statOrder":[null,861],
    "group":"FlaskFreezeAndChillImmunityDuringEffect",
    "affix":"of the Deer",
    "weightKey":[]
  },
  "FlaskFreezeAndChillImmunityDuringEffect2":{
    "weightVal":[],
    "modTags":[],
    "statOrder":[],
    "affix":"of the Walrus",
    "weightKey":[]
  },
  "FlaskBuffCurseEffect5":{
    "1":"(60-65)% reduced Effect of Curses on you during Effect",
    "level":84,
    "weightVal":[],
    "modTags":[],
    "statOrder":[879],
    "group":"FlaskBuffCurseEffect",
    "affix":"of the Owl",
    "weightKey":[]
  },
  "FlaskChargesUsed2":{
    "1":"(17-19)% reduced Charges per use",
    "level":31,
    "weightVal":[],
    "modTags":[],
    "statOrder":[],
    "affix":"Scholar's",
    "weightKey":[]
  },
  "FlaskFreezeAndChillImmunityDuringEffect3__":{
    "level":72,
    "weightVal":[],
    "modTags":[],
    "statOrder":[],
    "affix":"of the Penguin",
    "weightKey":[]
  },
  "FlaskBuffBleedDuration1":{
    "1":"(35-45)% reduced Bleeding Duration on you during Effect",
    "level":8,
    "weightVal":[],
    "modTags":[],
    "statOrder":[877],
    "group":"FlaskBuffBleedDuration",
    "affix":"[UNUSED] Bleed duration 1",
    "weightKey":[]
  },
  "FlaskChargesUsed3__":{
    "1":"(20-22)% reduced Charges per use",
    "level":48,
    "weightVal":[],
    "modTags":[],
    "statOrder":[],
    "affix":"Practitioner's",
    "weightKey":[]
  },
  "FlaskIgniteImmunityDuringEffect_":{
    "affix":"of the Urchin",
    "weightVal":[],
    "modTags":[],
    "statOrder":[],
    "weightKey":[]
  },
  "FlaskShockImmunityDuringEffect2___":{
    "weightVal":[],
    "modTags":[],
    "statOrder":[],
    "affix":"of the Moray",
    "weightKey":[]
  },
  "FlaskChargesUsed4__":{
    "1":"(23-25)% reduced Charges per use",
    "weightVal":[],
    "modTags":[],
    "statOrder":[],
    "affix":"Brewer's",
    "weightKey":[]
  },
  "FlaskShockImmunityDuringEffect":{
    "weightVal":[],
    "modTags":[],
    "statOrder":[],
    "affix":"of the Conger",
    "weightKey":[]
  },
  "FlaskPoisonImmunityDuringEffect":{
    "weightVal":[],
    "modTags":[],
    "statOrder":[],
    "affix":"of the Skunk",
    "weightKey":[]
  },
  "FlaskChargesUsed5":{
    "1":"(26-28)% reduced Charges per use",
    "weightVal":[],
    "modTags":[],
    "statOrder":[],
    "affix":"Chemist's",
    "weightKey":[]
  },
  "FlaskBuffIgniteDuration1_":{
    "1":"(35-45)% reduced Ignite Duration on you during Effect",
    "weightVal":[],
    "modTags":[],
    "statOrder":[881],
    "group":"FlaskBuffIgniteDuration",
    "affix":"[UNUSED] Ignite duration 1",
    "weightKey":[]
  },
  "FlaskIgniteImmunityDuringEffect3":{
    "affix":"of the Starfish",
    "weightVal":[],
    "modTags":[],
    "statOrder":[],
    "weightKey":[]
  },
  "FlaskIncreasedDuration2":{
    "1":"(16-20)% increased Duration",
    "weightVal":[],
    "modTags":[],
    "statOrder":[],
    "group":"FlaskUtilityIncreasedDuration",
    "affix":"Investigator's",
    "weightKey":[null,"critical_utility_flask"]
  },
  "FlaskBleedingAndCorruptedBloodImmunityDuringEffect_1":{
    "weightVal":[],
    "modTags":[],
    "statOrder":[],
    "affix":"of the Lizard",
    "weightKey":[]
  },
  "FlaskBuffAvoidChillFreeze1_":{
    "1":"(31-35)% chance to Avoid being Chilled during Effect",
    "2":"(31-35)% chance to Avoid being Frozen during Effect",
    "weightVal":[],
    "modTags":[],
    "statOrder":[843,844],
    "group":"FlaskBuffAvoidChillFreeze",
    "affix":"of the Orca",
    "weightKey":[]
  },
  "FlaskIgniteImmunity1":{
    "1":"Grants Immunity to Ignite for (6-8) seconds if used while Ignited",
    "weightVal":[],
    "modTags":[],
    "statOrder":[],
    "affix":"of Damping",
    "weightKey":[]
  },
  "FlaskIncreasedDuration3_":{
    "1":"(21-25)% increased Duration",
    "level":36,
    "weightVal":[],
    "modTags":[],
    "statOrder":[],
    "affix":"Analyst's",
    "weightKey":[]
  },
  "FlaskBleedingAndCorruptedBloodImmunityDuringEffect2_":{
    "level":42,
    "weightVal":[],
    "modTags":[],
    "statOrder":[],
    "affix":"of the Skink",
    "weightKey":[]
  },
  "FlaskHealsMinions2":{
    "1":"Grants (120-139)% of Life Recovery to Minions",
    "level":28,
    "weightVal":[],
    "modTags":[],
    "statOrder":[],
    "affix":"of the Acolyte",
    "weightKey":[]
  },
  "FlaskIncreasedDuration4":{
    "1":"(26-30)% increased Duration",
    "weightVal":[],
    "modTags":[],
    "statOrder":[],
    "affix":"Examiner's",
    "weightKey":[]
  },
  "FlaskShockImmunity4_":{
    "1":"Grants Immunity to Shock for (15-17) seconds if used while Shocked",
    "weightVal":[],
    "modTags":[],
    "statOrder":[791],
    "group":"FlaskShockImmunity",
    "affix":"of the Dielectric",
    "weightKey":[]
  },
  "FlaskShockImmunity3":{
    "1":"Grants Immunity to Shock for (12-14) seconds if used while Shocked",
    "weightVal":[],
    "modTags":[],
    "statOrder":[],
    "affix":"of Insulation",
    "weightKey":[]
  },
  "FlaskIncreasedDuration5__":{
    "1":"(31-35)% increased Duration",
    "level":68,
    "weightVal":[],
    "modTags":[],
    "statOrder":[],
    "affix":"Clinician's",
    "weightKey":[]
  },
  "FlaskBuffAvoidChillFreeze3":{
    "1":"(41-45)% chance to Avoid being Chilled during Effect",
    "2":"(41-45)% chance to Avoid being Frozen during Effect",
    "weightVal":[],
    "modTags":[],
    "statOrder":[],
    "affix":"of the Narwhal",
    "weightKey":[]
  },
  "FlaskShockImmunity2":{
    "1":"Grants Immunity to Shock for (9-11) seconds if used while Shocked",
    "weightVal":[],
    "modTags":[],
    "statOrder":[],
    "affix":"of Grounding",
    "weightKey":[]
  },
  "FlaskIncreasedDuration6":{
    "1":"(36-40)% increased Duration",
    "weightVal":[],
    "modTags":[],
    "statOrder":[],
    "affix":"Experimenter's",
    "weightKey":[]
  },
  "FlaskShockImmunity1":{
    "1":"Grants Immunity to Shock for (6-8) seconds if used while Shocked",
    "weightVal":[],
    "modTags":[],
    "statOrder":[],
    "affix":"of Earthing",
    "weightKey":[]
  },
  "FlaskBuffAvoidChillFreeze4":{
    "1":"(46-50)% chance to Avoid being Chilled during Effect",
    "2":"(46-50)% chance to Avoid being Frozen during Effect",
    "weightVal":[],
    "modTags":[],
    "statOrder":[],
    "affix":"of the Beluga",
    "weightKey":[]
  },
  "FlaskFullRechargeOnHit1":{
    "1":"Gain 1 Charge when you are Hit by an Enemy",
    "weightVal":[],
    "modTags":[],
    "statOrder":[723],
    "group":"FlaskFullRechargeOnHit",
    "affix":"Delinquent's",
    "weightKey":[]
  },
  "FlaskIncreasedRecoveryReducedEffect2_":{
    "1":"(43-48)% increased Charge Recovery",
    "2":"25% reduced effect",
    "weightVal":[],
    "modTags":[],
    "statOrder":[728],
    "group":"FlaskIncreasedRecoveryReducedEffect",
    "affix":"Provisioned",
    "weightKey":[]
  },
  "FlaskChargesAddedIncreasePercent4_":{
    "1":"(31-45)% increased Charge Recovery",
    "weightVal":[],
    "modTags":[],
    "statOrder":[],
    "group":"FlaskIncreasedChargesAdded",
    "affix":"Bottomless",
    "weightKey":[]
  },
  "FlaskBleedCorruptingBloodImmunity2":{
    "1":"Grants Immunity to Bleeding for (9-11) seconds if used while Bleeding",
    "2":"Grants Immunity to Corrupted Blood for (9-11) seconds if used while affected by Corrupted Blood",
    "level":32,
    "weightVal":[],
    "modTags":[],
    "statOrder":[781,781.1],
    "group":"FlaskBleedCorruptingBloodImmunity",
    "affix":"of Alleviation",
    "weightKey":[]
  },
  "FlaskFullRechargeOnHit2_":{
    "level":29,
    "weightVal":[],
    "modTags":[],
    "statOrder":[],
    "affix":"Transgressor's",
    "weightKey":[]
  },
  "FlaskBuffSpellEnergyShieldLeechWhileHealing2_":{
    "1":"0.5% of Spell Damage Leeched as Energy Shield during Effect",
    "weightVal":[],
    "modTags":[null,"defences","energy_shield","caster"],
    "statOrder":[830],
    "group":"FlaskBuffSpellEnergyShieldLeechWhileHealing",
    "affix":"of Depletion",
    "weightKey":[null,"expedition_flask"]
  },
  "FlaskFullRechargeOnHit3_":{
    "1":"Gain 2 Charges when you are Hit by an Enemy",
    "weightVal":[],
    "modTags":[],
    "statOrder":[],
    "affix":"Sinner's",
    "weightKey":[]
  },
  "FlaskBuffSpellEnergyShieldLeechWhileHealing4":{
    "1":"0.7% of Spell Damage Leeched as Energy Shield during Effect",
    "weightVal":[],
    "modTags":[],
    "statOrder":[],
    "affix":"of Siphoning",
    "weightKey":[]
  },
  "FlaskBuffAccuracyWhileHealing1__":{
    "1":"(15-25)% increased Accuracy Rating during Effect",
    "weightVal":[],
    "modTags":[],
    "statOrder":[823],
    "group":"FlaskBuffAccuracyWhileHealing",
    "affix":"of the Monkey",
    "weightKey":[]
  },
  "FlaskFullRechargeOnHit4_":{
    "weightVal":[],
    "modTags":[],
    "statOrder":[],
    "affix":"Masochist's",
    "weightKey":[]
  },
  "FlaskBuffCriticalChanceWhileHealing3":{
    "1":"(38-43)% increased Critical Strike Chance during Effect",
    "weightVal":[],
    "modTags":[null,"critical"],
    "statOrder":[855],
    "group":"FlaskBuffCriticalWhileHealing",
    "affix":"of Rupturing",
    "weightKey":[]
  },
  "FlaskFullRechargeOnHit5___":{
    "1":"Gain 3 Charges when you are Hit by an Enemy",
    "weightVal":[],
    "modTags":[],
    "statOrder":[],
    "affix":"Flagellant's",
    "weightKey":[]
  },
  "FlaskBuffCriticalChanceWhileHealing2_":{
    "1":"(32-37)% increased Critical Strike Chance during Effect",
    "level":34,
    "weightVal":[],
    "modTags":[],
    "statOrder":[],
    "affix":"of Piercing",
    "weightKey":[]
  },
  "LocalLifeFlaskAdditionalLifeRecovery1":{
    "1":"Recover an additional (11-16)% of Flask's Life Recovery Amount over 10 seconds if used while not on Full Life",
    "weightVal":[],
    "modTags":[],
    "statOrder":[779],
    "group":"LocalLifeFlaskAdditionalLifeRecovery",
    "affix":"of Abundance",
    "weightKey":["life_flask"]
  },
  "FlaskIncreasedHealingCharges1":{
    "1":"(20-25)% increased Charges per use",
    "2":"(21-26)% increased Amount Recovered",
    "weightVal":[],
    "modTags":[],
    "statOrder":[null,737],
    "group":"FlaskIncreasedHealingCharges",
    "affix":"Nitrate",
    "weightKey":[]
  },
  "FlaskDispellsChill1":{
    "1":"Grants Immunity to Chill for 4 seconds if used while Chilled",
    "2":"Grants Immunity to Freeze for 4 seconds if used while Frozen",
    "weightVal":[],
    "modTags":[null,null,"cold"],
    "statOrder":[782,782.1],
    "group":"FlaskDispellsChill",
    "affix":"of Heat",
    "weightKey":[]
  },
  "LocalFlaskImmuneToMaimAndHinder3":{
    "1":"Grants Immunity to Hinder for (12-14) seconds if used while Hindered",
    "2":"Grants Immunity to Maim for (12-14) seconds if used while Maimed",
    "weightVal":[],
    "modTags":[],
    "statOrder":[786,787],
    "group":"LocalFlaskImmuneToMaimAndHinder",
    "affix":"of Freedom",
    "weightKey":[]
  },
  "FlaskChanceRechargeOnCrit2":{
    "1":"(16-20)% chance to gain a Flask Charge when you deal a Critical Strike",
    "level":26,
    "weightVal":[],
    "modTags":[],
    "statOrder":[725],
    "group":"FlaskChanceRechargeOnCrit",
    "affix":"Physician's",
    "weightKey":[]
  },
  "LocalFlaskImmuneToMaimAndHinder1":{
    "1":"Grants Immunity to Hinder for (6-8) seconds if used while Hindered",
    "2":"Grants Immunity to Maim for (6-8) seconds if used while Maimed",
    "weightVal":[],
    "modTags":[],
    "statOrder":[],
    "affix":"of Movement",
    "weightKey":[]
  },
  "FlaskIncreasedHealingCharges2":{
    "2":"(27-32)% increased Amount Recovered",
    "weightVal":[],
    "modTags":[],
    "statOrder":[],
    "affix":"Dolomite",
    "weightKey":[]
  },
  "LocalLifeFlaskHinderNearbyEnemies4":{
    "1":"Hinders nearby Enemies with (35-40)% reduced Movement Speed if used while not on Full Life",
    "weightVal":[],
    "modTags":[],
    "statOrder":[792],
    "group":"LocalLifeFlaskHinderNearbyEnemies",
    "affix":"of Restraint",
    "weightKey":[]
  },
  "LocalLifeFlaskHinderNearbyEnemies3_":{
    "1":"Hinders nearby Enemies with (29-34)% reduced Movement Speed if used while not on Full Life",
    "level":66,
    "weightVal":[],
    "modTags":[],
    "statOrder":[],
    "affix":"of Occlusion",
    "weightKey":[]
  },
  "FlaskIncreasedHealingCharges3":{
    "2":"(33-38)% increased Amount Recovered",
    "weightVal":[],
    "modTags":[],
    "statOrder":[],
    "affix":"Kieserite",
    "weightKey":[]
  },
  "LocalLifeFlaskHinderNearbyEnemies2_":{
    "1":"Hinders nearby Enemies with (23-28)% reduced Movement Speed if used while not on Full Life",
    "weightVal":[],
    "modTags":[],
    "statOrder":[],
    "affix":"of Obstruction",
    "weightKey":[]
  },
  "FlaskIncreasedRecoveryAmount3":{
    "1":"(53-58)% increased Amount Recovered",
    "2":"33% reduced Recovery rate",
    "weightVal":[],
    "modTags":[],
    "statOrder":[null,738],
    "group":"FlaskIncreasedRecoveryAmount",
    "affix":"Full-bodied",
    "weightKey":[]
  },
  "FlaskIncreasedHealingCharges4____":{
    "2":"(39-44)% increased Amount Recovered",
    "weightVal":[],
    "modTags":[],
    "statOrder":[],
    "affix":"Kainite",
    "weightKey":[]
  },
  "FlaskChargesAddedIncreasePercent2_":{
    "1":"(21-25)% increased Charge Recovery",
    "level":23,
    "weightVal":[],
    "modTags":[],
    "statOrder":[],
    "affix":"Continuous",
    "weightKey":[]
  },
  "FlaskInstantRecoveryOnLowLife5__":{
    "1":"(11-14)% reduced Amount Recovered",
    "2":"Instant Recovery when on Low Life",
    "weightVal":[],
    "modTags":[],
    "statOrder":[null,743],
    "group":"FlaskInstantRecoveryOnLowLife",
    "affix":"Panicked",
    "weightKey":[]
  },
  "FlaskIncreasedHealingCharges5":{
    "2":"(45-50)% increased Amount Recovered",
    "weightVal":[],
    "modTags":[],
    "statOrder":[],
    "affix":"Gypsum",
    "weightKey":[]
  },
  "LocalManaFlaskHinderNearbyEnemies2":{
    "1":"Hinders nearby Enemies with (23-28)% reduced Movement Speed if used while not on Full Mana",
    "weightVal":[],
    "modTags":[],
    "statOrder":[793],
    "group":"LocalManaFlaskHinderNearbyEnemies",
    "weightKey":[]
  },
  "LocalManaFlaskHinderNearbyEnemies1_":{
    "1":"Hinders nearby Enemies with (17-22)% reduced Movement Speed if used while not on Full Mana",
    "weightVal":[],
    "modTags":[],
    "statOrder":[],
    "affix":"of Interference",
    "weightKey":[]
  },
  "FlaskManaRecoveryAtEnd1_":{
    "1":"66% increased Amount Recovered",
    "2":"Mana Recovery occurs instantly at the end of Effect",
    "weightVal":[null,null,3000],
    "modTags":[],
    "statOrder":[null,748],
    "group":"FlaskManaRecoveryAtEnd",
    "affix":"Foreboding",
    "weightKey":[]
  },
  "FlaskBuffWardWhileHealing1":{
    "1":"(19-21)% increased Ward during Effect",
    "weightVal":[],
    "modTags":[],
    "statOrder":[819],
    "group":"FlaskBuffWardWhileHealing",
    "affix":"of Runegleaming",
    "weightKey":[]
  },
  "FlaskBuffAvoidShock5":{
    "1":"(51-55)% chance to Avoid being Shocked during Effect",
    "weightVal":[],
    "modTags":[],
    "statOrder":[846],
    "group":"FlaskBuffAvoidShock",
    "affix":"of Bog Moss",
    "weightKey":[]
  },
  "FlaskBuffAvoidShock4_____":{
    "1":"(46-50)% chance to Avoid being Shocked during Effect",
    "weightVal":[],
    "modTags":[],
    "statOrder":[],
    "affix":"of Plume Moss",
    "weightKey":[]
  },
  "FlaskBuffAvoidShock3":{
    "1":"(41-45)% chance to Avoid being Shocked during Effect",
    "weightVal":[],
    "modTags":[],
    "statOrder":[],
    "affix":"of Tooth Moss",
    "weightKey":[]
  },
  "FlaskEffectNotRemovedOnFullMana1":{
    "1":"66% reduced Amount Recovered",
    "2":"Effect is not removed when Unreserved Mana is Filled",
    "3":"Effect does not Queue",
    "affix":"Enduring",
    "weightVal":[],
    "modTags":[],
    "statOrder":[null,747,747.1],
    "group":"FlaskEffectNotRemovedOnFullManaReducedRecovery",
    "weightKey":[]
  },
  "FlaskBuffAvoidShock2_":{
    "1":"(36-40)% chance to Avoid being Shocked during Effect",
    "weightVal":[],
    "modTags":[],
    "statOrder":[],
    "affix":"of Turf Moss",
    "weightKey":[]
  },
  "FlaskBuffAvoidShock1":{
    "1":"(31-35)% chance to Avoid being Shocked during Effect",
    "weightVal":[],
    "modTags":[],
    "statOrder":[],
    "affix":"of Tree Moss",
    "weightKey":[]
  },
  "FlaskBuffAvoidIgnite5_":{
    "1":"(51-55)% chance to Avoid being Ignited during Effect",
    "weightVal":[],
    "modTags":[],
    "statOrder":[845],
    "group":"FlaskBuffAvoidIgnite",
    "affix":"of the Sunfish",
    "weightKey":[]
  },
  "FlaskExtraManaCostsLife2":{
    "1":"(47-52)% increased Mana Recovered",
    "2":"Removes 15% of Mana Recovered from Life when used",
    "weightVal":[],
    "modTags":[],
    "statOrder":[736,752],
    "group":"FlaskExtraManaCostsLife",
    "affix":"Fermented",
    "weightKey":[null,null,"hybrid_flask"]
  },
  "FlaskBuffAttackLifeLeechWhileHealing1":{
    "1":"0.4% of Attack Damage Leeched as Life during Effect",
    "weightVal":[],
    "modTags":[],
    "statOrder":[831],
    "group":"FlaskBuffAttackLifeLeechWhileHealing",
    "affix":"of Bloodshed",
    "weightKey":[]
  },
  "FlaskBuffAvoidIgnite4___":{
    "1":"(46-50)% chance to Avoid being Ignited during Effect",
    "weightVal":[],
    "modTags":[],
    "statOrder":[],
    "affix":"of the Catfish",
    "weightKey":[]
  },
  "FlaskExtraManaCostsLife3_":{
    "1":"(53-58)% increased Mana Recovered",
    "level":47,
    "weightVal":[],
    "modTags":[],
    "statOrder":[],
    "affix":"Congealed",
    "weightKey":[]
  },
  "FlaskBuffAvoidIgnite1":{
    "1":"(31-35)% chance to Avoid being Ignited during Effect",
    "weightVal":[],
    "modTags":[],
    "statOrder":[],
    "affix":"of the Guppy",
    "weightKey":[]
  },
  "FlaskBuffAttackLifeLeechWhileHealing2":{
    "1":"0.5% of Attack Damage Leeched as Life during Effect",
    "weightVal":[],
    "modTags":[],
    "statOrder":[],
    "affix":"of Gore",
    "weightKey":[]
  },
  "FlaskExtraManaCostsLife4":{
    "1":"(59-64)% increased Mana Recovered",
    "weightVal":[],
    "modTags":[],
    "statOrder":[],
    "affix":"Turbid",
    "weightKey":[]
  },
  "FlaskBuffAvoidIgnite3":{
    "1":"(41-45)% chance to Avoid being Ignited during Effect",
    "weightVal":[],
    "modTags":[],
    "statOrder":[],
    "affix":"of the Carp",
    "weightKey":[]
  },
  "FlaskBuffAttackLifeLeechWhileHealing3":{
    "1":"0.6% of Attack Damage Leeched as Life during Effect",
    "weightVal":[],
    "modTags":[],
    "statOrder":[],
    "affix":"of Carnage",
    "weightKey":[]
  },
  "FlaskExtraManaCostsLife5_":{
    "1":"(65-70)% increased Mana Recovered",
    "weightVal":[],
    "modTags":[],
    "statOrder":[],
    "affix":"Caustic",
    "weightKey":[]
  },
  "FlaskBuffAvoidIgnite2":{
    "1":"(36-40)% chance to Avoid being Ignited during Effect",
    "weightVal":[],
    "modTags":[],
    "statOrder":[],
    "affix":"of the Goldfish",
    "weightKey":[]
  },
  "FlaskBuffAttackLifeLeechWhileHealing4":{
    "1":"0.7% of Attack Damage Leeched as Life during Effect",
    "weightVal":[],
    "modTags":[],
    "statOrder":[],
    "affix":"of Butchery",
    "weightKey":[]
  },
  "FlaskExtraLifeCostsMana1":{
    "1":"(35-39)% increased Life Recovered",
    "2":"Removes 10% of Life Recovered from Mana when used",
    "level":13,
    "weightVal":[],
    "modTags":[],
    "statOrder":[732,754],
    "group":"FlaskExtraLifeCostsMana",
    "affix":"Impairing",
    "weightKey":[]
  },
  "FlaskBuffAvoidChillFreeze5":{
    "1":"(51-55)% chance to Avoid being Chilled during Effect",
    "2":"(51-55)% chance to Avoid being Frozen during Effect",
    "weightVal":[],
    "modTags":[],
    "statOrder":[],
    "affix":"of the Seal",
    "weightKey":[]
  },
  "FlaskBuffAttackLifeLeechWhileHealing5":{
    "1":"0.8% of Attack Damage Leeched as Life during Effect",
    "weightVal":[],
    "modTags":[],
    "statOrder":[],
    "affix":"of Bloodletting",
    "weightKey":[]
  },
  "FlaskBuffAvoidChillFreeze2":{
    "1":"(36-40)% chance to Avoid being Chilled during Effect",
    "2":"(36-40)% chance to Avoid being Frozen during Effect",
    "weightVal":[],
    "modTags":[],
    "statOrder":[],
    "affix":"of the Sea Lion",
    "weightKey":[]
  },
  "FlaskBuffPoisonDuration1":{
    "1":"(35-45)% reduced Poison Duration on you during Effect",
    "weightVal":[],
    "modTags":[],
    "statOrder":[882],
    "group":"FlaskBuffPoisonDuration",
    "affix":"[UNUSED] Poison duration 1",
    "weightKey":[]
  },
  "FlaskBuffSpellEnergyShieldLeechWhileHealing1":{
    "1":"0.4% of Spell Damage Leeched as Energy Shield during Effect",
    "weightVal":[],
    "modTags":[],
    "statOrder":[],
    "affix":"of Diverting",
    "weightKey":[]
  },
  "FlaskBuffCurseEffect4":{
    "1":"(52-59)% reduced Effect of Curses on you during Effect",
    "weightVal":[],
    "modTags":[],
    "statOrder":[],
    "affix":"of the Kakapo",
    "weightKey":[]
  },
  "FlaskBuffCurseEffect3_":{
    "1":"(48-52)% reduced Effect of Curses on you during Effect",
    "weightVal":[],
    "modTags":[],
    "statOrder":[],
    "affix":"of the Curlew",
    "weightKey":[]
  },
  "FlaskExtraLifeCostsMana3":{
    "1":"(46-50)% increased Life Recovered",
    "weightVal":[],
    "modTags":[],
    "statOrder":[],
    "affix":"Depleting",
    "weightKey":[]
  },
  "FlaskBuffCurseEffect2":{
    "1":"(42-47)% reduced Effect of Curses on you during Effect",
    "level":27,
    "weightVal":[],
    "modTags":[],
    "statOrder":[],
    "affix":"of the Mockingbird",
    "weightKey":[]
  },
  "FlaskBuffCurseEffect1":{
    "1":"(36-41)% reduced Effect of Curses on you during Effect",
    "weightVal":[],
    "modTags":[],
    "statOrder":[],
    "affix":"of the Petrel",
    "weightKey":[]
  },
  "FlaskExtraLifeCostsMana4":{
    "1":"(51-55)% increased Life Recovered",
    "weightVal":[],
    "modTags":[],
    "statOrder":[],
    "affix":"Vitiating",
    "weightKey":[]
  },
  "FlaskBuffWardWhileHealing2_":{
    "1":"(22-24)% increased Ward during Effect",
    "weightVal":[],
    "modTags":[],
    "statOrder":[],
    "affix":"of Runeshining",
    "weightKey":[]
  },
  "FlaskBuffShockEffect5":{
    "1":"(60-65)% reduced Effect of Shock on you during Effect",
    "weightVal":[],
    "modTags":[],
    "statOrder":[],
    "affix":"of the Heron",
    "weightKey":[]
  },
  "FlaskExtraLifeCostsMana5_":{
    "1":"(56-60)% increased Life Recovered",
    "weightVal":[],
    "modTags":[],
    "statOrder":[],
    "affix":"Sapping",
    "weightKey":[]
  },
  "FlaskBuffWardWhileHealing3":{
    "1":"(25-27)% increased Ward during Effect",
    "weightVal":[],
    "modTags":[],
    "statOrder":[],
    "affix":"of Runeflaring",
    "weightKey":[]
  },
  "FlaskBuffChillFreezeDuration5":{
    "1":"(60-65)% reduced Effect of Chill on you during Effect",
    "2":"(60-65)% reduced Freeze Duration on you during Effect",
    "weightVal":[],
    "modTags":[],
    "statOrder":[878,880],
    "group":"FlaskBuffChillFreezeDuration",
    "affix":"of the Bear",
    "weightKey":[]
  },
  "FlaskIncreasedRecoverySpeed1":{
    "1":"(41-46)% increased Recovery rate",
    "weightVal":[],
    "modTags":[],
    "statOrder":[],
    "group":"FlaskIncreasedRecoverySpeed",
    "affix":"Undiluted",
    "weightKey":[]
  },
  "FlaskBuffWardWhileHealing4":{
    "1":"(28-30)% increased Ward during Effect",
    "weightVal":[],
    "modTags":[],
    "statOrder":[],
    "affix":"of Runeblazing",
    "weightKey":[]
  },
  "FlaskBuffChillFreezeDuration4":{
    "1":"(52-59)% reduced Effect of Chill on you during Effect",
    "2":"(52-59)% reduced Freeze Duration on you during Effect",
    "weightVal":[],
    "modTags":[],
    "statOrder":[],
    "affix":"of the Sable",
    "weightKey":[]
  },
  "FlaskBuffSpellEnergyShieldLeechWhileHealing5":{
    "1":"0.8% of Spell Damage Leeched as Energy Shield during Effect",
    "weightVal":[],
    "modTags":[],
    "statOrder":[],
    "affix":"of Draining",
    "weightKey":[]
  },
  "FlaskHealsMinions1":{
    "1":"Grants (100-119)% of Life Recovery to Minions",
    "weightVal":[],
    "modTags":[],
    "statOrder":[],
    "affix":"of the Novice",
    "weightKey":[]
  },
  "FlaskBuffChillFreezeDuration3_":{
    "1":"(48-52)% reduced Effect of Chill on you during Effect",
    "2":"(48-52)% reduced Freeze Duration on you during Effect",
    "weightVal":[],
    "modTags":[],
    "statOrder":[],
    "affix":"of the Fox",
    "weightKey":[]
  },
  "FlaskBuffAttackSpeedWhileHealing1":{
    "1":"(9-11)% increased Attack Speed during Effect",
    "weightVal":[],
    "modTags":[],
    "statOrder":[824],
    "group":"FlaskBuffAttackSpeedWhileHealing",
    "affix":"of the Falcon",
    "weightKey":[]
  },
  "FlaskCurseImmunity1":{
    "1":"Removes Curses on use",
    "level":18,
    "weightVal":[],
    "modTags":[null,null,"curse"],
    "statOrder":[778],
    "group":"FlaskCurseImmunity",
    "affix":"of Warding",
    "weightKey":[]
  },
  "FlaskBuffChillFreezeDuration1":{
    "1":"(36-41)% reduced Effect of Chill on you during Effect",
    "2":"(36-41)% reduced Freeze Duration on you during Effect",
    "weightVal":[],
    "modTags":[],
    "statOrder":[],
    "affix":"of the Rabbit",
    "weightKey":[]
  },
  "FlaskDispellsBurning1":{
    "1":"Grants Immunity to Ignite for 4 seconds if used while Ignited",
    "weightVal":[],
    "modTags":[null,null,"fire"],
    "statOrder":[784,784.1],
    "group":"FlaskDispellsBurning",
    "affix":"of Dousing",
    "weightKey":[]
  },
  "FlaskBuffAttackSpeedWhileHealing2_____":{
    "1":"(12-14)% increased Attack Speed during Effect",
    "level":62,
    "weightVal":[],
    "modTags":[],
    "statOrder":[],
    "affix":"of the Eagle",
    "weightKey":[]
  },
  "FlaskIncreasedRecoveryReducedEffect4_":{
    "1":"(55-60)% increased Charge Recovery",
    "weightVal":[],
    "modTags":[],
    "statOrder":[],
    "affix":"Allocated",
    "weightKey":[]
  },
  "FlaskHealsMinions3":{
    "1":"Grants (140-159)% of Life Recovery to Minions",
    "weightVal":[],
    "modTags":[],
    "statOrder":[],
    "affix":"of the Summoner",
    "weightKey":[]
  },
  "FlaskBuffAttackSpeedWhileHealing3_":{
    "1":"(15-17)% increased Attack Speed during Effect",
    "weightVal":[],
    "modTags":[],
    "statOrder":[],
    "affix":"of the Dove",
    "weightKey":[]
  },
  "FlaskIncreasedRecoverySpeed2":{
    "1":"(47-52)% increased Recovery rate",
    "weightVal":[],
    "modTags":[],
    "statOrder":[],
    "affix":"Thickened",
    "weightKey":[]
  },
  "FlaskRemovesBleeding1":{
    "1":"Grants Immunity to Bleeding for 4 seconds if used while Bleeding",
    "2":"Grants Immunity to Corrupted Blood for 4 seconds if used while affected by Corrupted Blood",
    "weightVal":[],
    "modTags":[null,"bleed"],
    "statOrder":[780,780.1],
    "group":"FlaskRemovesBleeding",
    "affix":"of Staunching",
    "weightKey":[]
  },
  "FlaskBuffCastSpeedWhileHealing1":{
    "1":"(9-11)% increased Cast Speed during Effect",
    "weightVal":[],
    "modTags":[],
    "statOrder":[825],
    "group":"FlaskBuffCastSpeedWhileHealing",
    "affix":"of the Albatross",
    "weightKey":[]
  },
  "FlaskIncreasedRecoverySpeed3_":{
    "1":"(53-58)% increased Recovery rate",
    "weightVal":[],
    "modTags":[],
    "statOrder":[],
    "affix":"Viscous",
    "weightKey":[]
  },
  "FlaskHealsMinions5":{
    "1":"Grants (180-200)% of Life Recovery to Minions",
    "weightVal":[],
    "modTags":[],
    "statOrder":[],
    "affix":"of the Necromancer",
    "weightKey":[]
  },
  "LocalManaFlaskHinderNearbyEnemies3":{
    "1":"Hinders nearby Enemies with (29-34)% reduced Movement Speed if used while not on Full Mana",
    "weightVal":[],
    "modTags":[],
    "statOrder":[],
    "weightKey":[]
  },
  "FlaskIncreasedRecoverySpeed4":{
    "1":"(59-64)% increased Recovery rate",
    "weightVal":[],
    "modTags":[],
    "statOrder":[],
    "affix":"Condensed",
    "weightKey":[]
  },
  "FlaskFullRechargeOnCrit1":{
    "1":"Recharges 1 Charge when you deal a Critical Strike",
    "weightVal":[],
    "modTags":[],
    "statOrder":[724],
    "group":"FlaskFullRechargeOnCrit",
    "affix":"Surgeon's",
    "weightKey":[]
  },
  "LocalManaFlaskHinderNearbyEnemies4":{
    "1":"Hinders nearby Enemies with (35-40)% reduced Movement Speed if used while not on Full Mana",
    "weightVal":[],
    "modTags":[],
    "statOrder":[],
    "weightKey":[]
  },
  "FlaskRemovesShock1":{
    "1":"Grants Immunity to Shock for 4 seconds if used while Shocked",
    "weightVal":[],
    "modTags":[null,null,"lightning"],
    "statOrder":[790],
    "group":"FlaskRemovesShock",
    "weightKey":[]
  },
  "FlaskChargesAddedIncreasePercent3_":{
    "1":"(26-30)% increased Charge Recovery",
    "level":43,
    "weightVal":[],
    "modTags":[],
    "statOrder":[],
    "affix":"Endless",
    "weightKey":[]
  },
  "LocalLifeFlaskHinderNearbyEnemies1_":{
    "1":"Hinders nearby Enemies with (17-22)% reduced Movement Speed if used while not on Full Life",
    "weightVal":[],
    "modTags":[],
    "statOrder":[],
    "weightKey":[]
  },
  "FlaskIncreasedRecoveryAmount1":{
    "1":"(41-46)% increased Amount Recovered",
    "weightVal":[],
    "modTags":[],
    "statOrder":[],
    "affix":"Substantial",
    "weightKey":[]
  },
  "FlaskChanceRechargeOnCrit1":{
    "1":"(11-15)% chance to gain a Flask Charge when you deal a Critical Strike",
    "weightVal":[],
    "modTags":[],
    "statOrder":[],
    "affix":"Medic's",
    "weightKey":[]
  },
  "FlaskExtraCharges1":{
    "1":"+(16-19) to Maximum Charges",
    "level":2,
    "weightVal":[],
    "modTags":[],
    "statOrder":[720],
    "group":"FlaskExtraMaxCharges",
    "affix":"Wide",
    "weightKey":[]
  },
  "FlaskIncreasedRecoveryReducedEffect3____":{
    "1":"(49-54)% increased Charge Recovery",
    "weightVal":[],
    "modTags":[],
    "statOrder":[],
    "affix":"Measured",
    "weightKey":[]
  },
  "FlaskBuffAccuracyWhileHealing2":{
    "1":"(26-35)% increased Accuracy Rating during Effect",
    "weightVal":[],
    "modTags":[],
    "statOrder":[],
    "affix":"of the Raccoon",
    "weightKey":[]
  },
  "FlaskIncreasedRecoveryAmount2_":{
    "1":"(47-52)% increased Amount Recovered",
    "weightVal":[],
    "modTags":[],
    "statOrder":[],
    "affix":"Opaque",
    "weightKey":[]
  },
  "FlaskExtraCharges2__":{
    "1":"+(20-23) to Maximum Charges",
    "level":22,
    "weightVal":[],
    "modTags":[],
    "statOrder":[],
    "affix":"Plentiful",
    "weightKey":[]
  },
  "FlaskBuffAccuracyWhileHealing3":{
    "1":"(35-45)% increased Accuracy Rating during Effect",
    "weightVal":[],
    "modTags":[],
    "statOrder":[],
    "affix":"of the Crow",
    "weightKey":[]
  },
  "FlaskChanceRechargeOnCrit3___":{
    "1":"(21-25)% chance to gain a Flask Charge when you deal a Critical Strike",
    "weightVal":[],
    "modTags":[],
    "statOrder":[],
    "affix":"Doctor's",
    "weightKey":[]
  },
  "FlaskExtraCharges3_":{
    "1":"+(24-27) to Maximum Charges",
    "weightVal":[],
    "modTags":[],
    "statOrder":[],
    "affix":"Bountiful",
    "weightKey":[]
  },
  "FlaskBuffCriticalChanceWhileHealing1_":{
    "1":"(26-31)% increased Critical Strike Chance during Effect",
    "weightVal":[],
    "modTags":[],
    "statOrder":[],
    "affix":"of Stinging",
    "weightKey":[]
  },
  "FlaskIncreasedRecoveryAmount4":{
    "1":"(59-64)% increased Amount Recovered",
    "weightVal":[],
    "modTags":[],
    "statOrder":[],
    "affix":"Concentrated",
    "weightKey":[]
  },
  "FlaskExtraCharges4__":{
    "1":"+(28-31) to Maximum Charges",
    "weightVal":[],
    "modTags":[],
    "statOrder":[],
    "affix":"Abundant",
    "weightKey":[]
  },
  "LocalFlaskImmuneToMaimAndHinder2":{
    "1":"Grants Immunity to Hinder for (9-11) seconds if used while Hindered",
    "2":"Grants Immunity to Maim for (9-11) seconds if used while Maimed",
    "weightVal":[],
    "modTags":[],
    "statOrder":[],
    "affix":"of Motion",
    "weightKey":[]
  },
  "FlaskChanceRechargeOnCrit5":{
    "1":"(31-35)% chance to gain a Flask Charge when you deal a Critical Strike",
    "weightVal":[],
    "modTags":[],
    "statOrder":[],
    "weightKey":[]
  },
  "FlaskExtraCharges5":{
    "1":"+(32-35) to Maximum Charges",
    "weightVal":[],
    "modTags":[],
    "statOrder":[],
    "affix":"Ample",
    "weightKey":[]
  },
  "FlaskFullRechargeOnTakeCrit1":{
    "1":"Recharges 5 Charges when you take a Critical Strike",
    "weightVal":[],
    "modTags":[],
    "statOrder":[727],
    "group":"FlaskFullRechargeOnTakeCrit",
    "affix":"Avenger's",
    "weightKey":[]
  },
  "FlaskIncreasedRecoveryOnLowLife1":{
    "1":"(101-106)% more Recovery if used while on Low Life",
    "weightVal":[],
    "modTags":[],
    "statOrder":[742],
    "group":"FlaskIncreasedRecoveryOnLowLife",
    "affix":"Prudent",
    "weightKey":[]
  },
  "FlaskChargesAddedIncreasePercent1":{
    "1":"(16-20)% increased Charge Recovery",
    "level":3,
    "weightVal":[],
    "modTags":[],
    "statOrder":[],
    "affix":"Constant",
    "weightKey":[]
  },
  "FlaskBuffEvasionWhileHealing3_":{
    "1":"(51-55)% increased Evasion Rating during Effect",
    "level":58,
    "weightVal":[],
    "modTags":[null,null,"evasion"],
    "statOrder":[817],
    "group":"FlaskBuffEvasionWhileHealing",
    "affix":"of the Ibex",
    "weightKey":[]
  },
  "FlaskBuffCriticalChanceWhileHealing4__":{
    "1":"(44-49)% increased Critical Strike Chance during Effect",
    "weightVal":[],
    "modTags":[],
    "statOrder":[],
    "affix":"of Penetrating",
    "weightKey":[]
  },
  "LocalFlaskImmuneToMaimAndHinder4":{
    "1":"Grants Immunity to Hinder for (15-17) seconds if used while Hindered",
    "2":"Grants Immunity to Maim for (15-17) seconds if used while Maimed",
    "weightVal":[],
    "modTags":[],
    "statOrder":[],
    "affix":"of Liberation",
    "weightKey":[]
  },
  "FlaskIncreasedRecoveryOnLowLife2_":{
    "1":"(107-112)% more Recovery if used while on Low Life",
    "weightVal":[],
    "modTags":[],
    "statOrder":[],
    "affix":"Prepared",
    "weightKey":[]
  },
  "FlaskBuffCriticalChanceWhileHealing5":{
    "1":"(50-55)% increased Critical Strike Chance during Effect",
    "weightVal":[],
    "modTags":[],
    "statOrder":[],
    "affix":"of Incision",
    "weightKey":[]
  },
  "FlaskBuffAvoidStunWhileHealing1_":{
    "1":"(31-35)% Chance to Avoid being Stunned during Effect",
    "weightVal":[],
    "modTags":[],
    "statOrder":[851],
    "group":"FlaskBuffAvoidStunWhileHealing",
    "affix":"of Composure",
    "weightKey":[]
  },
  "FlaskIncreasedRecoveryOnLowLife3":{
    "1":"(113-118)% more Recovery if used while on Low Life",
    "weightVal":[],
    "modTags":[],
    "statOrder":[],
    "affix":"Wary",
    "weightKey":[]
  },
  "FlaskBuffFreezeShockIgniteChanceWhileHealing1_":{
    "1":"(19-22)% chance to Freeze, Shock and Ignite during Effect",
    "weightVal":[],
    "modTags":[],
    "statOrder":[853],
    "group":"FlaskBuffFreezeShockIgniteChanceWhileHealing",
    "affix":"of Foisting",
    "weightKey":[]
  },
  "FlaskBuffCastSpeedWhileHealing3":{
    "1":"(15-17)% increased Cast Speed during Effect",
    "weightVal":[],
    "modTags":[],
    "statOrder":[],
    "affix":"of the Horsefly",
    "weightKey":[]
  },
  "FlaskIncreasedRecoveryOnLowLife4":{
    "1":"(119-124)% more Recovery if used while on Low Life",
    "weightVal":[],
    "modTags":[],
    "statOrder":[],
    "affix":"Careful",
    "weightKey":[]
  },
  "LocalLifeFlaskAdditionalLifeRecovery2__":{
    "1":"Recover an additional (17-22)% of Flask's Life Recovery Amount over 10 seconds if used while not on Full Life",
    "level":39,
    "weightVal":[],
    "modTags":[],
    "statOrder":[],
    "affix":"of Plenty",
    "weightKey":[]
  },
  "FlaskBuffFreezeShockIgniteChanceWhileHealing2____":{
    "1":"(23-26)% chance to Freeze, Shock and Ignite during Effect",
    "weightVal":[],
    "modTags":[],
    "statOrder":[],
    "affix":"of Imposing",
    "weightKey":[]
  },
  "FlaskIncreasedRecoveryOnLowLife5":{
    "1":"(125-130)% more Recovery if used while on Low Life",
    "weightVal":[],
    "modTags":[],
    "statOrder":[],
    "affix":"Cautious",
    "weightKey":[]
  },
  "LocalLifeFlaskAdditionalLifeRecovery3":{
    "1":"Recover an additional (23-28)% of Flask's Life Recovery Amount over 10 seconds if used while not on Full Life",
    "level":53,
    "weightVal":[],
    "modTags":[],
    "statOrder":[],
    "affix":"of Bounty",
    "weightKey":[]
  },
  "FlaskBuffFreezeShockIgniteChanceWhileHealing3":{
    "1":"(27-30)% chance to Freeze, Shock and Ignite during Effect",
    "weightVal":[],
    "modTags":[],
    "statOrder":[],
    "affix":"of Wreaking",
    "weightKey":[]
  },
  "FlaskInstantRecoveryOnLowLife1":{
    "1":"(27-30)% reduced Amount Recovered",
    "weightVal":[],
    "modTags":[],
    "statOrder":[],
    "affix":"Startled",
    "weightKey":[]
  },
  "LocalLifeFlaskAdditionalLifeRecovery4":{
    "1":"Recover an additional (29-34)% of Flask's Life Recovery Amount over 10 seconds if used while not on Full Life",
    "level":67,
    "weightVal":[],
    "modTags":[],
    "statOrder":[],
    "affix":"of Incessance",
    "weightKey":[]
  },
  "FlaskBuffFreezeShockIgniteChanceWhileHealing4_":{
    "1":"(31-34)% chance to Freeze, Shock and Ignite during Effect",
    "weightVal":[],
    "modTags":[],
    "statOrder":[],
    "affix":"of Infliction",
    "weightKey":[]
  },
  "FlaskBuffCastSpeedWhileHealing2":{
    "1":"(12-14)% increased Cast Speed during Effect",
    "weightVal":[],
    "modTags":[],
    "statOrder":[],
    "affix":"of the Hummingbird",
    "weightKey":[]
  },
  "LocalLifeFlaskAdditionalLifeRecovery5_":{
    "1":"Recover an additional (35-40)% of Flask's Life Recovery Amount over 10 seconds if used while not on Full Life",
    "weightVal":[],
    "modTags":[],
    "statOrder":[],
    "affix":"of Perenniality",
    "weightKey":[]
  },
  "FlaskInstantRecoveryOnLowLife2":{
    "1":"(23-26)% reduced Amount Recovered",
    "weightVal":[],
    "modTags":[],
    "statOrder":[],
    "affix":"Frightened",
    "weightKey":[]
  },
  "FlaskBuffSpellEnergyShieldLeechWhileHealing3_____":{
    "1":"0.6% of Spell Damage Leeched as Energy Shield during Effect",
    "weightVal":[],
    "modTags":[],
    "statOrder":[],
    "affix":"of Tapping",
    "weightKey":[]
  },
  "FlaskBleedCorruptingBloodImmunity1":{
    "1":"Grants Immunity to Bleeding for (6-8) seconds if used while Bleeding",
    "2":"Grants Immunity to Corrupted Blood for (6-8) seconds if used while affected by Corrupted Blood",
    "weightVal":[],
    "modTags":[],
    "statOrder":[],
    "affix":"of Sealing",
    "weightKey":[]
  },
  "FlaskInstantRecoveryOnLowLife3":{
    "1":"(19-22)% reduced Amount Recovered",
    "level":45,
    "weightVal":[],
    "modTags":[],
    "statOrder":[],
    "affix":"Alarmed",
    "weightKey":[]
  },
  "FlaskBuffAvoidStunWhileHealing2":{
    "1":"(36-40)% Chance to Avoid being Stunned during Effect",
    "weightVal":[],
    "modTags":[],
    "statOrder":[],
    "affix":"of Surefootedness",
    "weightKey":[]
  },
  "FlaskIncreasedRecoveryReducedEffect1_":{
    "1":"(37-42)% increased Charge Recovery",
    "weightVal":[],
    "modTags":[],
    "statOrder":[],
    "affix":"Doled",
    "weightKey":[]
  },
  "FlaskInstantRecoveryOnLowLife4":{
    "1":"(15-18)% reduced Amount Recovered",
    "weightVal":[],
    "modTags":[],
    "statOrder":[],
    "affix":"Terrified",
    "weightKey":[]
  },
  "FlaskBuffAvoidStunWhileHealing3":{
    "1":"(41-45)% Chance to Avoid being Stunned during Effect",
    "weightVal":[],
    "modTags":[],
    "statOrder":[],
    "affix":"of Persistence",
    "weightKey":[]
  },
  "FlaskChargesAddedIncreasePercent5__":{
    "1":"(46-50)% increased Charge Recovery",
    "level":83,
    "weightVal":[],
    "modTags":[],
    "statOrder":[],
    "affix":"Perpetual",
    "weightKey":[]
  },
  "FlaskIncreasedRecoveryReducedEffect5":{
    "1":"(61-66)% increased Charge Recovery",
    "weightVal":[],
    "modTags":[],
    "statOrder":[],
    "affix":"Rationed",
    "weightKey":[]
  },
  "FlaskBuffAvoidStunWhileHealing4":{
    "1":"(46-50)% Chance to Avoid being Stunned during Effect",
    "weightVal":[],
    "modTags":[],
    "statOrder":[],
    "affix":"of Relentlessness",
    "weightKey":[]
  },
  "FlaskBleedCorruptingBloodImmunity3______":{
    "1":"Grants Immunity to Bleeding for (12-14) seconds if used while Bleeding",
    "2":"Grants Immunity to Corrupted Blood for (12-14) seconds if used while affected by Corrupted Blood",
    "level":56,
    "weightVal":[],
    "modTags":[],
    "statOrder":[],
    "affix":"of Allaying",
    "weightKey":[]
  },
  "FlaskBuffArmourWhileHealing1":{
    "1":"(41-45)% increased Armour during Effect",
    "weightVal":[],
    "modTags":[null,null,"armour"],
    "statOrder":[816],
    "group":"FlaskBuffArmourWhileHealing",
    "affix":"of the Abalone",
    "weightKey":[]
  },
  "FlaskBuffAvoidStunWhileHealing5":{
    "1":"(51-55)% Chance to Avoid being Stunned during Effect",
    "weightVal":[],
    "modTags":[],
    "statOrder":[],
    "affix":"of Tenaciousness",
    "weightKey":[]
  },
  "FlaskPartialInstantRecovery1":{
    "1":"(52-55)% reduced Amount Recovered",
    "2":"135% increased Recovery rate",
    "3":"50% of Recovery applied Instantly",
    "affix":"Simmering",
    "weightVal":[],
    "modTags":[],
    "statOrder":[null,null,744],
    "group":"FlaskPartialInstantRecovery",
    "weightKey":[]
  },
  "FlaskBleedCorruptingBloodImmunity4_":{
    "1":"Grants Immunity to Bleeding for (15-17) seconds if used while Bleeding",
    "2":"Grants Immunity to Corrupted Blood for (15-17) seconds if used while affected by Corrupted Blood",
    "weightVal":[],
    "modTags":[],
    "statOrder":[],
    "affix":"of Assuaging",
    "weightKey":[]
  },
  "FlaskBuffReducedManaCostWhileHealing1_":{
    "1":"(11-14)% reduced Mana Cost of Skills during Effect",
    "weightVal":[],
    "modTags":[],
    "statOrder":[873],
    "group":"LocalFlaskSkillManaCostDuringFlaskEffect",
    "affix":"of the Pupil",
    "weightKey":[]
  },
  "FlaskIncreasedRecoverySpeed5":{
    "1":"(65-70)% increased Recovery rate",
    "weightVal":[],
    "modTags":[],
    "statOrder":[],
    "affix":"Catalysed",
    "weightKey":[]
  },
  "FlaskPartialInstantRecovery2":{
    "1":"(48-51)% reduced Amount Recovered",
    "affix":"Ebullient",
    "weightVal":[],
    "modTags":[],
    "statOrder":[],
    "weightKey":[]
  },
  "FlaskBuffArmourWhileHealing2":{
    "1":"(46-50)% increased Armour during Effect",
    "weightVal":[],
    "modTags":[],
    "statOrder":[],
    "affix":"of the Tortoise",
    "weightKey":[]
  },
  "FlaskBuffReducedManaCostWhileHealing2__":{
    "1":"(15-18)% reduced Mana Cost of Skills during Effect",
    "weightVal":[],
    "modTags":[],
    "statOrder":[],
    "affix":"of the Initiate",
    "weightKey":[]
  },
  "FlaskPartialInstantRecovery3":{
    "1":"(44-47)% reduced Amount Recovered",
    "affix":"Effusive",
    "weightVal":[],
    "modTags":[],
    "statOrder":[],
    "weightKey":[]
  },
  "FlaskBuffArmourWhileHealing3":{
    "1":"(51-55)% increased Armour during Effect",
    "weightVal":[],
    "modTags":[],
    "statOrder":[],
    "affix":"of the Pangolin",
    "weightKey":[]
  },
  "FlaskBuffReducedManaCostWhileHealing3":{
    "1":"(19-21)% reduced Mana Cost of Skills during Effect",
    "weightVal":[],
    "modTags":[],
    "statOrder":[],
    "affix":"of the Mage",
    "weightKey":[]
  },
  "FlaskPartialInstantRecovery4":{
    "1":"(40-43)% reduced Amount Recovered",
    "affix":"Effervescent",
    "weightVal":[],
    "modTags":[],
    "statOrder":[],
    "weightKey":[]
  },
  "FlaskBuffArmourWhileHealing4":{
    "1":"(56-60)% increased Armour during Effect",
    "weightVal":[],
    "modTags":[],
    "statOrder":[],
    "affix":"of the Armadillo",
    "weightKey":[]
  },
  "FlaskBuffReducedManaCostWhileHealing4":{
    "1":"(22-25)% reduced Mana Cost of Skills during Effect",
    "weightVal":[],
    "modTags":[],
    "statOrder":[],
    "affix":"of the Arcanist",
    "weightKey":[]
  },
  "FlaskPartialInstantRecovery5_":{
    "1":"(36-39)% reduced Amount Recovered",
    "level":79,
    "affix":"Bubbling",
    "weightVal":[],
    "modTags":[],
    "statOrder":[],
    "weightKey":[]
  },
  "FlaskBuffEvasionWhileHealing":{
    "1":"(41-45)% increased Evasion Rating during Effect",
    "weightVal":[],
    "modTags":[],
    "statOrder":[],
    "affix":"of the Gazelle",
    "weightKey":[]
  },
  "FlaskBuffReducedManaCostWhileHealing5":{
    "1":"(26-29)% reduced Mana Cost of Skills during Effect",
    "weightVal":[],
    "modTags":[],
    "statOrder":[],
    "affix":"of the Sorcerer",
    "weightKey":[]
  },
  "FlaskFullInstantRecovery1":{
    "2":"Instant Recovery",
    "level":7,
    "weightVal":[],
    "modTags":[],
    "statOrder":[null,749],
    "group":"FlaskFullInstantRecovery",
    "affix":"Seething",
    "weightKey":[]
  },
  "FlaskChillFreezeImmunity1":{
    "1":"Grants Immunity to Chill for (6-8) seconds if used while Chilled",
    "2":"Grants Immunity to Freeze for (6-8) seconds if used while Frozen",
    "weightVal":[],
    "modTags":[],
    "statOrder":[],
    "affix":"of Convection",
    "weightKey":[]
  },
  "FlaskBuffEvasionWhileHealing2":{
    "1":"(46-50)% increased Evasion Rating during Effect",
    "weightVal":[],
    "modTags":[],
    "statOrder":[],
    "affix":"of the Antelope",
    "weightKey":[]
  },
  "FlaskChanceRechargeOnCrit4":{
    "1":"(26-30)% chance to gain a Flask Charge when you deal a Critical Strike",
    "weightVal":[],
    "modTags":[],
    "statOrder":[],
    "affix":"Specialist's",
    "weightKey":[]
  },
  "FlaskIncreasedRecoveryAmount5":{
    "1":"(65-70)% increased Amount Recovered",
    "weightVal":[],
    "modTags":[],
    "statOrder":[],
    "affix":"Saturated",
    "weightKey":[]
  },
  "FlaskExtraManaCostsLife1":{
    "1":"(41-46)% increased Mana Recovered",
    "weightVal":[],
    "modTags":[],
    "statOrder":[],
    "affix":"Aged",
    "weightKey":[]
  },
  "FlaskChillFreezeImmunity2":{
    "1":"Grants Immunity to Chill for (9-11) seconds if used while Chilled",
    "2":"Grants Immunity to Freeze for (9-11) seconds if used while Frozen",
    "weightVal":[],
    "modTags":[],
    "statOrder":[],
    "affix":"of Thermodynamics",
    "weightKey":[]
  },
  "FlaskBuffChillFreezeDuration2_":{
    "1":"(42-47)% reduced Effect of Chill on you during Effect",
    "2":"(42-47)% reduced Freeze Duration on you during Effect",
    "weightVal":[],
    "modTags":[],
    "statOrder":[],
    "affix":"of the Cat",
    "weightKey":[]
  },
  "FlaskBuffEvasionWhileHealing4":{
    "1":"(56-60)% increased Evasion Rating during Effect",
    "weightVal":[],
    "modTags":[],
    "statOrder":[],
    "affix":"of the Impala",
    "weightKey":[]
  },
  "FlaskExtraLifeCostsMana2":{
    "1":"(40-44)% increased Life Recovered",
    "weightVal":[],
    "modTags":[],
    "statOrder":[],
    "affix":"Dizzying",
    "weightKey":[]
  }
}