{
  "NecropolisCraftingAccuracyPer2Dexterity":{
    "group":"AccuracyPer2Dexterity",
    "modTags":[],
    "statOrder":[4289],
    "weightKey":[],
    "weightVal":[],
    "1":"+2 to Accuracy Rating per 2 Dexterity"
  },
  "NecropolisCraftingAllResistancesWithChaos":{
    "group":"AllResistancesWithChaos",
    "modTags":[],
    "statOrder":[9208],
    "weightKey":[],
    "weightVal":[1000],
    "1":"+(12-16)% to All Resistances"
  },
  "NecropolisCraftingArcaneSurgeOnSpendingMana":{
    "group":"ArcaneSurgeOnSpendingMana",
    "modTags":[],
    "statOrder":[6633],
    "weightKey":[],
    "weightVal":[],
    "1":"Gain Arcane Surge after Spending a total of 400 Mana"
  },
  "NecropolisCraftingAreaOfEffect":{
    "group":"AreaOfEffect",
    "level":12,
    "modTags":[],
    "statOrder":[1741],
    "weightKey":[],
    "weightVal":[],
    "1":"(15-25)% increased Area of Effect"
  },
  "NecropolisCraftingAvoidFreeze":{
    "group":"AvoidFreeze",
    "modTags":[],
    "statOrder":[1706],
    "weightKey":[],
    "weightVal":[],
    "1":"(60-75)% chance to Avoid being Frozen"
  },
  "NecropolisCraftingAvoidIgnite":{
    "group":"AvoidIgnite",
    "level":16,
    "modTags":[null,"elemental","fire"],
    "statOrder":[1707],
    "weightKey":[],
    "weightVal":[],
    "1":"(60-75)% chance to Avoid being Ignited"
  },
  "NecropolisCraftingAvoidShock":{
    "group":"AvoidShock",
    "modTags":[null,null,"lightning"],
    "statOrder":[1709],
    "weightKey":[],
    "weightVal":[],
    "1":"(60-75)% chance to Avoid being Shocked"
  },
  "NecropolisCraftingBurningGroundEffectEffectiveness":{
    "group":"BurningGroundEffectEffectiveness",
    "modTags":[],
    "statOrder":[9702],
    "weightKey":[],
    "weightVal":[],
    "1":"Unaffected by Burning Ground"
  },
  "NecropolisCraftingCannotBeKnockedBack":{
    "group":"CannotBeKnockedBack",
    "modTags":[],
    "statOrder":[1384],
    "weightKey":[],
    "weightVal":[],
    "1":"Cannot be Knocked Back"
  },
  "NecropolisCraftingChanceToBleed":{
    "group":"ChanceToBleed",
    "modTags":[],
    "statOrder":[2342],
    "weightKey":[],
    "weightVal":[],
    "1":"Attacks have (15-25)% chance to cause Bleeding"
  },
  "NecropolisCraftingChaosDamage":{
    "group":"ChaosDamage",
    "modTags":["chaos_damage"],
    "statOrder":[1253],
    "weightKey":[],
    "weightVal":[750],
    "1":"Adds (13-17) to (23-29) Chaos Damage to Attacks"
  },
  "NecropolisCraftingChilledGroundEffectEffectiveness":{
    "group":"ChilledGroundEffectEffectiveness",
    "modTags":[],
    "statOrder":[9707],
    "weightKey":[],
    "weightVal":[],
    "1":"Unaffected by Chilled Ground"
  },
  "NecropolisCraftingColdResistanceCannotBePenetrated":{
    "group":"ColdResistanceCannotBePenetrated",
    "modTags":[null,null,"cold"],
    "statOrder":[5425],
    "weightKey":[],
    "weightVal":[],
    "1":"Cold Resistance cannot be Penetrated"
  },
  "NecropolisCraftingCorruptedBloodImmunity":{
    "group":"CorruptedBloodImmunity",
    "level":60,
    "modTags":[],
    "statOrder":[5008],
    "weightKey":[],
    "weightVal":[],
    "1":"Corrupted Blood cannot be inflicted on you"
  },
  "NecropolisCraftingCriticalStrikeChance":{
    "group":"CriticalStrikeChance",
    "modTags":[],
    "statOrder":[1323],
    "weightKey":[],
    "weightVal":[],
    "1":"(30-50)% increased Global Critical Strike Chance"
  },
  "NecropolisCraftingCriticalStrikeMultiplier":{
    "group":"CriticalStrikeMultiplier",
    "modTags":[null,"damage","critical"],
    "statOrder":[1352],
    "weightKey":[],
    "weightVal":[],
    "1":"+(15-25)% to Global Critical Strike Multiplier"
  },
  "NecropolisCraftingCurseEffectiveness":{
    "group":"CurseEffectiveness",
    "modTags":[null,null,"curse"],
    "statOrder":[2449],
    "weightKey":[],
    "weightVal":[],
    "1":"(5-8)% increased Effect of your Curses"
  },
  "NecropolisCraftingDamageTakenGainedAsLife":{
    "group":"DamageTakenGainedAsLife",
    "level":45,
    "modTags":["resource",null,"life"],
    "statOrder":[5680],
    "weightKey":[],
    "weightVal":[],
    "1":"(25-35)% of Damage taken Recouped as Life"
  },
  "NecropolisCraftingDesecratedGroundEffectEffectiveness":{
    "group":"DesecratedGroundEffectEffectiveness",
    "modTags":[],
    "statOrder":[9713],
    "weightKey":[],
    "weightVal":[],
    "1":"Unaffected by Desecrated Ground"
  },
  "NecropolisCraftingFasterBleedDamage":{
    "group":"FasterBleedDamage",
    "modTags":["physical_damage"],
    "statOrder":[6082],
    "weightKey":[],
    "weightVal":[],
    "1":"Bleeding you inflict deals Damage (12-20)% faster"
  },
  "NecropolisCraftingFireResistanceCannotBePenetrated":{
    "group":"FireResistanceCannotBePenetrated",
    "level":68,
    "modTags":[null,null,null,"resistance"],
    "statOrder":[6121],
    "weightKey":["necropolis_body_armour"],
    "weightVal":[],
    "1":"Fire Resistance cannot be Penetrated"
  },
  "NecropolisCraftingGlobalChanceToBlindOnHit":{
    "group":"GlobalChanceToBlindOnHit",
    "modTags":[],
    "statOrder":[2806],
    "weightKey":["necropolis_gloves"],
    "weightVal":[],
    "1":"(15-25)% Global chance to Blind Enemies on hit"
  },
  "NecropolisCraftingGlobalMaimOnHit":{
    "group":"GlobalMaimOnHit",
    "modTags":[],
    "statOrder":[7577],
    "weightKey":[],
    "weightVal":[],
    "1":"Attacks have (15-25)% chance to Maim on Hit"
  },
  "NecropolisCraftingImmunityToBlind":{
    "group":"ImmunityToBlind",
    "modTags":[],
    "statOrder":[2822],
    "weightKey":[],
    "weightVal":[],
    "1":"Cannot be Blinded"
  },
  "NecropolisCraftingIncreasedCastSpeed":{
    "group":"IncreasedCastSpeed",
    "level":1,
    "modTags":[null,"caster","speed"],
    "statOrder":[1310],
    "weightKey":["necropolis_helmet"],
    "weightVal":[500],
    "1":"(8-12)% increased Cast Speed"
  },
  "NecropolisCraftingIncreasedMaximumPowerCharges":{
    "group":"IncreasedMaximumPowerCharges",
    "modTags":["power_charge"],
    "statOrder":[1675],
    "weightKey":[],
    "weightVal":[],
    "1":"+1 to Maximum Power Charges"
  },
  "NecropolisCraftingIncreasedStunThreshold":{
    "group":"IncreasedStunThreshold",
    "modTags":[],
    "statOrder":[3115],
    "weightKey":[],
    "weightVal":[],
    "1":"(80-120)% increased Stun Threshold"
  },
  "NecropolisCraftingIntimidateOnHit":{
    "group":"IntimidateOnHit",
    "level":38,
    "modTags":[],
    "statOrder":[4645],
    "weightKey":[],
    "weightVal":[],
    "1":"(15-25)% chance to Intimidate Enemies for 4 seconds on Hit with Attacks"
  },
  "NecropolisCraftingLifeReservationEfficiency":{
    "group":"LifeReservationEfficiency",
    "modTags":[],
    "statOrder":[2081],
    "weightKey":[],
    "weightVal":[],
    "1":"(20-30)% increased Life Reservation Efficiency of Skills"
  },
  "NecropolisCraftingLightningResistanceCannotBePenetrated":{
    "group":"LightningResistanceCannotBePenetrated",
    "modTags":[],
    "statOrder":[6927],
    "weightKey":[],
    "weightVal":[],
    "1":"Lightning Resistance cannot be Penetrated"
  },
  "NecropolisCraftingLocalCanSocketIgnoringColour":{
    "group":"LocalCanSocketIgnoringColour",
    "modTags":[],
    "statOrder":[71],
    "weightKey":[],
    "weightVal":[],
    "1":"Gems can be Socketed in this Item ignoring Socket Colour"
  },
  "NecropolisCraftingLocalNoAttributeRequirements":{
    "group":"LocalNoAttributeRequirements",
    "level":50,
    "modTags":[],
    "statOrder":[955],
    "weightKey":[],
    "weightVal":[],
    "1":"Has no Attribute Requirements"
  },
  "NecropolisCraftingManaPer2Intelligence":{
    "group":"ManaPer2Intelligence",
    "modTags":[],
    "statOrder":[8535],
    "weightKey":[],
    "weightVal":[100],
    "1":"+1 to maximum Mana per 2 Intelligence"
  },
  "NecropolisCraftingManaRegeneration":{
    "group":"ManaRegeneration",
    "modTags":[],
    "statOrder":[1446],
    "weightKey":[],
    "weightVal":[],
    "1":"(40-60)% increased Mana Regeneration Rate"
  },
  "NecropolisCraftingManaReservationEfficiency":{
    "group":"ManaReservationEfficiency",
    "modTags":[null,null,"mana"],
    "statOrder":[2083],
    "weightKey":[],
    "weightVal":[],
    "1":"(10-15)% increased Mana Reservation Efficiency of Skills"
  },
  "NecropolisCraftingMaximumEnduranceCharges":{
    "group":"MaximumEnduranceCharges",
    "modTags":["endurance_charge"],
    "statOrder":[1665],
    "weightKey":[],
    "weightVal":[],
    "1":"+1 to Maximum Endurance Charges"
  },
  "NecropolisCraftingMaximumFrenzyCharges":{
    "affix":"Haunted",
    "group":"MaximumFrenzyCharges",
    "modTags":["frenzy_charge"],
    "statOrder":[1670],
    "type":"Prefix",
    "weightKey":[],
    "weightVal":[],
    "1":"+1 to Maximum Frenzy Charges"
  },
  "NecropolisCraftingMeleeKnockback":{
    "group":"MeleeKnockback",
    "modTags":[],
    "statOrder":[8552],
    "weightKey":[],
    "weightVal":[],
    "1":"Melee Attacks Knock Enemies Back on Hit"
  },
  "NecropolisCraftingMovementCannotBeSlowedBelowBase":{
    "group":"MovementCannotBeSlowedBelowBase",
    "modTags":[],
    "statOrder":[3037],
    "weightKey":[],
    "weightVal":[],
    "1":"Movement Speed cannot be modified to below Base Value"
  },
  "NecropolisCraftingNoExtraBleedDamageWhileMoving":{
    "affix":"of Haunting",
    "group":"NoExtraBleedDamageWhileMoving",
    "level":34,
    "modTags":["bleed","necropolis_exclusive_mod","physical","attack","ailment"],
    "statOrder":[3033],
    "type":"Suffix",
    "weightKey":["necropolis_boots","default"],
    "weightVal":[250,0],
    "1":"Moving while Bleeding doesn't cause you to take extra Damage"
  },
  "NecropolisCraftingPercentDamageGoesToMana":{
    "group":"PercentDamageGoesToMana",
    "modTags":[],
    "statOrder":[2308],
    "weightKey":[],
    "weightVal":[],
    "1":"(25-35)% of Damage taken Recouped as Mana"
  },
  "NecropolisCraftingPoisonDuration":{
    "group":"PoisonDuration",
    "modTags":[],
    "statOrder":[3011],
    "weightKey":[],
    "weightVal":[],
    "1":"(12-20)% increased Poison Duration"
  },
  "NecropolisCraftingPoisonOnHit":{
    "group":"PoisonOnHit",
    "modTags":[],
    "statOrder":[3014],
    "weightKey":[],
    "weightVal":[],
    "1":"(15-25)% chance to Poison on Hit"
  },
  "NecropolisCraftingReducedBleedDuration":{
    "group":"ReducedBleedDuration",
    "level":24,
    "modTags":[],
    "statOrder":[9249],
    "weightKey":[],
    "weightVal":[350],
    "1":"(60-75)% reduced Bleed Duration on you"
  },
  "NecropolisCraftingReducedExtraDamageFromCrits":{
    "group":"ReducedExtraDamageFromCrits",
    "modTags":[],
    "statOrder":[1375],
    "weightKey":[],
    "weightVal":[],
    "1":"You take (40-60)% reduced Extra Damage from Critical Strikes"
  },
  "NecropolisCraftingReducedPoisonDuration":{
    "group":"ReducedPoisonDuration",
    "modTags":["poison",null,"chaos"],
    "statOrder":[9257],
    "weightKey":[],
    "weightVal":[],
    "1":"(60-75)% reduced Poison Duration on you"
  },
  "NecropolisCraftingShockedGroundEffectEffectiveness":{
    "group":"ShockedGroundEffectEffectiveness",
    "modTags":[],
    "statOrder":[9727],
    "weightKey":[],
    "weightVal":[],
    "1":"Unaffected by Shocked Ground"
  },
  "NecropolisCraftingSpellDamage":{
    "group":"SpellDamage",
    "modTags":["caster_damage"],
    "statOrder":[1092],
    "weightKey":[],
    "weightVal":[],
    "1":"(20-30)% increased Spell Damage"
  },
  "NecropolisCraftingSpellUnnerveOnHit":{
    "group":"SpellUnnerveOnHit",
    "modTags":[],
    "statOrder":[5321],
    "weightKey":[],
    "weightVal":[],
    "1":"(15-25)% chance to Unnerve Enemies for 4 seconds on Hit with Spells"
  },
  "NecropolisCraftingSpellsHinderOnHitChance":{
    "group":"SpellsHinderOnHitChance",
    "modTags":[],
    "statOrder":[9448],
    "weightKey":[],
    "weightVal":[],
    "1":"(15-25)% chance to Hinder Enemies on Hit with Spells"
  },
  "NecropolisCraftingWarcriesOpenChests":{
    "group":"WarcriesOpenChests",
    "modTags":[],
    "statOrder":[8869],
    "weightKey":[],
    "weightVal":[],
    "1":"Your Warcries open Chests"
  }
}